Workbook

Sheet FORMULARIO
A3: =IFERROR('Analisis garantia'!BF14,"") -> A | C3: =IFERROR('Analisis garantia'!BF17,"") -> Tasa a Ofrecer | I3: =IFERROR('Analisis de pago'!I6,"") | K3: =IF(I3="","","Calificacion según analisis de pago")
C4: =IFERROR('Analisis garantia'!BF18,"") -> 2.5% - 3.5%
A7: Información General del solicitante
A9: Primer Nombre | F9: Segundo nombre | J9: Edad
A11: Primer apellido | F11: Segundo apellido
A13: Estado Civil | E13: Dirección de residencia
A15: Departamento | G15: Zona | I15: Municipio
A17: Numero de teléfono fijo | G17: Numero de celular
A19: compañía ? | G19: e-mail
A21: Medio en el que nos vio ? | H21: Coinciden direcciones?
H22: *al revisar datos llenar este campo
A24: Información laboral
A26: Ocupación | F26: Empresa
A28: Inicio de labores | F28: Afiliación al IGSS | I28: Numero de afiliación
A30: Ingresos | G30: Egresos
A32: Capacidad de endeudamiento | E32: =B30-H30 -> 0
A34: Dentro de sus egresos paga alguna deuda?
A36: Tiene dependientes económicos? | G36: Cuantos dependientes?
A38: Es usted profesional? | E38: Esta orgulloso de sus actividades
A41: Información crediticia
A43: Tiene cuenta en algún banco ? | G43: Estados de cuenta ?
A45: Tiene o ha tenido tarjeta de crédito? | G45: La tiene al día?
A47: El dinero lo utilizara en ….? | E47: Salud o Medico | H47: Ha tenido algún crédito ?
A49: Cuantos créditos activos tiene? | G49: Monto total que adeuda?
A51: Cuota mensual total? | F51: Capacidad de endeudamiento después de deudas | I51: =E32-D51 -> 0 | K51: =IFERROR(I51/B30,"")
A53: Posee cuotas atrasadas? | F53: Cantidad de cuotas atrasadas?
A55: Monto que requiere ? | F55: Vivienda propia ? | I55: vehículo propio?
A57: Es honrado? | D57: *Responder al revisar en buro crediticio
A59: Información del crédito
A61: Garantía del crédito | D61: Vehículo | G61: Tipo de crédito
A62: Monto requerido
A63: Tasa de interés | F63: =(D63*0.12)+D63 -> 0 | H63: Nivel
A64: Plazo | G64: cuota nivelada ideal | I64: =IFERROR(E32/I63,"")
A65: GPS
A66: Seguro
A67: Cuota nivelada | D67: =IFERROR(IF(A67="Cuota Nivelada",PMT(F63,D64,-D62)+D65+D66,(D62*F63)+D65+D66),0) -> 0 | F67: =IFERROR(D67/H69,"") | H67: Porcentaje que representa la cuota de su capacidad de endeudamiento
A69: Capacidad de endeudamiento después de deudas | H69: =I51 -> 0
A71: Diferencia entre cuota y capacidad de endeudamiento | H71: =H69-D67 -> 0 | I71: =IFERROR(1-F67,"")
A73: ¿La garantía es propia? | E73: Nombre del propietario de la garantía
A75: ¿Toma usted la decisión sobre el crédito ? | H75: ¿Que espera usted de su crédito?
A77: ¿Tiene algún pariente migrante ? | G77: contacto del pariente migrante
A79: Si llegara a tener algún problema de pago tiene alguien que lo apoye?
A81: Contacto del pariente
A84: Información de la garantía hipotecaria
A86: Tipo de propiedad | F86: Dirección exacta de la propiedad
A88: Departamento | G88: Municipio | J88: Zona
A90: Tiene construcción? | E90: Cuando se construyo?
A92: Referencia de ubicación de la propiedad | H92: cuenta con alguna deuda sobre la propiedad ?
A94: cual es el monto de la deuda? | G94: =IF(E94>=(E96*0.5),"Excede el 50% del valor bancario","Menor al 50% del valor bancario") -> Excede el 50% del valor bancario
A96: valor estimado/ esperado ? | G96: =IF(D62>=(E96*0.5),"Excede el 50% del valor","Monto ideal para crédito") -> Excede el 50% del valor | J96: =IFERROR(D62/E96,"")
A98: Tiene IUSI al día? | F98: Cuantos trimestres adeuda?
A100: Que logro tener algo propio! | F100: * ¿animado o se mostro parco en su respuesta?
A103: Información de la garantía vehículo
A105: Marca | E105: modelo / año | H105: línea
A107: Origen del vehículo | G107: Su vehículo se encuentra en estado
A109: Tipo de vehículo | E109: Le ha colocado accesorios o equipo de sonido mejorado
A111: Le ha realizado alguna modificación estética? | G111: en donde maneja su vehículo?
A113: Cuenta con alguna deuda sobre el vehículo ?
A115: Cual es el monto de la deuda ? | G115: =IF(E115>=(E117*0.5),"Excede el 50% del valor bancario","Menor al 50% del valor bancario") -> Excede el 50% del valor bancario
A117: Valor bancario del activo
A119: Impuesto de circulación del año en curso pagado? | I119: Días en mora?
A121: Que logro tener algo propio! | F121: * ¿animado o se mostro parco en su respuesta?
A123: Porcentaje que representa el monto solicitado sobre el valor bancario del activo | J123: =IFERROR(D62/E117,"")
A125: Observaciones

Sheet Hoja1
B3: Nombre del propietario | C3: =IF(FORMULARIO!I73="","",FORMULARIO!I73)
B4: Nombre del deudor | C4: =FORMULARIO!C9&Hoja1!C2&FORMULARIO!H9&Hoja1!C2&FORMULARIO!C11&Hoja1!C2&FORMULARIO!H11

Sheet Detalle vehiculo
B1: Detalle de crédito compra de vehiculo
B4: Nombre del Propietario: | C4: AUTOMAQ GUATEMALA, S.A.
B5: Nombre del deudor: | C5: Mario Edú Polanco Fores
B6: Nit del deudor: | D6: 43441726
B7: Garantía | C7: CAMION
B8: Datos: | C8: FOTON CAMION AUMARK E 2026
B9: Inversionista:
A11: ► | B11: MONTO SOLICITADO EN QUETZALES: | I11: =' Cotizador cliente'!C12+' Cotizador cliente'!C18+' Cotizador cliente'!C19 -> 133905.76
G13: % | H13: IVA
B14: Tasa de Interés: | C14: 0.015 | E14: Inversionista | G14: =(I11*C14)*70% -> 1406.0105 | H14: =G14*0.12 -> 168.72126 | I14: =I11*C14*C15 -> 0
A15: ► | B15: MES INTERES ANTICIPADO | C15: 0 | E15: Empresa | G15: =(I11*C14)*30% -> 602.57593 | H15: =G15*0.12 -> 72.309112 | I15: =I14*12/100 -> 0
E16: Inversionista | G16: =G14+H14 -> 1574.7318 | I16: =SUM(I14:I15) -> 0
E17: Empresa | G17: =G15+H15 -> 674.88504
A18: ► | B18: COMISION Y GASTOS DE REGISTRO
D19: Descontado
B20: ROYALTY | D20: SI | G20: 0.04 | H20: =' Cotizador cliente'!D22 -> 5064
B21: Free lance | D21: NO | G21: 0 | H21: =(I11)*G21 -> 0
B22: Free Lance | D22: NO | G22: 0 | H22: =I11*G22 -> 0
B23: Inspección | D23: NO | H23: 0
B24: GPS | D24: NO | H24: 0
B25: Seguro INREXSA | D25: SI | H25: ='Cotizador interno'!C16 -> 805.56
B26: Membresía | D26: SI | H26: ='Cotizador interno'!C19 -> 537.2024
B27: Gastos Administrativos | D27: SI | H27: =' Cotizador cliente'!F22 -> 600
B28: Intereses | D28: SI | H28: =' Cotizador cliente'!G22-H24-H25-H26 -> 2254 | I28: =H20+H21+H27+H24+H25+H26+H28 -> 9260.7624
B30: OTROS DESCUENTOS
B31: Nombramiento | D31: SI | H31: 150
B32: Multas | D32: NO | H32: 0
B33: Copia de llave | D33: NO | H33: 0
B34: Diferencia de copia de llave | D34: NO | H34: 0
B35: Verificación de dirección | D35: SI | H35: 395
B36: Impuesto circulación, 2025 | D36: NO | H36: 0
B37: Traspaso de vehículo | D37: NO | H37: 0
B38: Garantía mobiliaria | D38: SI | H38: =' Cotizador cliente'!E22 -> 400
I39: =SUM(H31:H38) -> 945
B41: GASTOS DE ABOGADO
B42: =IF(B37="Registro de Garantías Mobiliarias","Contrato de Garantía Mobiliaria","Contrato Leasing") -> Contrato Leasing | D42: SI | G42: 1 | H42: 400
B43: Autentica contrato de cobranza | D43: NO
B45: Vehículo comercial
B46: Valor Mercado | C46: 137000
B47: Valor Comercial
B48: Valor Bancario | I48: =SUM(H42:H48) -> 400
H49: DESCUENTOS DE:
B50: Capacidad de Pago | C50: 32329.36 | I50: =I28+I39+I48 -> 10605.762
B51: Prodencia del vehiculo | C51: AGENCIA | H51: TOTAL A RECIBIR:
B52: Edad solicitante (s) | C52: 44 | I52: =I11-I50 -> 123300
B53: Oportunidad | C53: 66090

Sheet Detalle cliente vehiculo
B15: Solicitante: | C15: Mario Edú Polanco Fores
B16: Vehiculo: | C16: FOTON CAMION AUMARK E 2026
B17: Inversionista: | C17: ='Detalle vehiculo'!C9 -> 0
B19: Monto Solicitado | D19: ='Detalle vehiculo'!I11 -> 133905.76
B21: Deducciones
B22: Cuotas interes mensual (interes sobre saldo) | C22: ='Detalle vehiculo'!I16 -> 0
B23: Royalty | C23: ='Detalle vehiculo'!H20 -> 5064
B24: Gastos de Traspaso | C24: ='Detalle vehiculo'!H21+'Detalle vehiculo'!H27+'Detalle vehiculo'!I39 -> 1545
A25: * | B25: Cuotas de seguro (12 cuotas anuales) | C25: 496.53
A26: * | B26: Cuotas de GPS (mensual) | C26: 148.2
B27: Gastos legales | C27: ='Detalle vehiculo'!I48 -> 400 | D27: =SUM(C22:C27) -> 7653.73
B28: Líquido a recibir | D28: =D19-D27 -> 126252.03
B30: *La prima del seguro son 12 cuotas anuales que se pagan mensualmente, al momento de cancelar el credito se cancela el seguro.
B31: *El GPS se paga mensualmente, se cancela al momento de desinstalar el dispositivo GPS.
B33: Nota: El pago de GPS y Seguro son obligatorios y no estan incuidos dentro de la cuota mensual de interes.

Sheet Detalle hipotecario
C4: DETALLE DE GASTOS DE PRÉSTAMO OTORGADO
G11: 43790
B14: Nombre del Propietario: | C14: =FORMULARIO!I73 -> 0
B15: Nombre del Solicitante del crédito: | C15: Mario Oswaldo Rosales Pur
B16: Dirección del Inmueble: | C16: =FORMULARIO!I86 -> 0
B17: Datos del inmueble: | C17: Finca 139, folio 139, libro 2538 de Guatemala
C18: Inversionista:
A20: ► | B20: MONTO SOLICITADO EN QUETZALES: | G20: =C21*E21 -> 300000.01
B21: Tipo de cambio: US$ 1.00 x Q. | C21: 7.7 | E21: 38961.04
E22: % | F22: IVA
B23: Tasa de Interés: | C23: 0.03 | D23: Inversionista | E23: =G20*1.5/100 -> 4500.0001 | F23: =(E23)*12/100 -> 540.00001
A24: ► | B24: MES INTERES ANTICIPADO | C24: 1 | D24: Empresa Club C | E24: =G20*0.5/100 -> 1500 | F24: =(E24)*12/100 -> 180 | G24: =G20*C23*C24 -> 9000.0002
C25: IVA | F25: =(E25)*12/100 -> 0 | G25: =G24*12/100 -> 1080
D26: =D23 -> Inversionista | E26: =E23+F23 -> 5040.0001 | G26: =SUM(G24:G25) -> 10080
D27: =D24 -> Empresa Club C | E27: =SUM(E24:F24) -> 1680
D28: =D25 -> 0 | E28: =(E25)+(F25) -> 0
A29: ► | B29: COMISION Y GASTOS DE REGISTRO
B31: Royalty | E31: 0.04 | F31: =G20*E31 -> 12000 | G31: =SUM(F31:F36) -> 16591.25
B32: Otros Gastos | E32: 0.01 | F32: =G20*E32 -> 3000.0001
B33: IUSI | F33: 0
B34: Gastos administrativos | F34: 600
B35: Seguro | F35: 0
B36: Gastos de Registro (Registro Propiedad Inmueble) | F36: ='Cálculo RGPI'!C26 -> 991.25
B37: Otros Gastos
B39: GASTOS ESCRITURACION Y REGISTRO
B40: Memorial para registro temporal e inscripción RGPI | F40: 0
B41: Otros descuentos | F41: 0
G42: =SUM(F40:F41) -> 0
A44: ► | B44: GASTOS DE ABOGADO | G44: =SUM(F45:F50) -> 4060.0001
B45: Honorarios Escrituración | E45: 0.01 | F45: =(G20)*(E45)+(100) -> 3100.0001
B46: IVA | E46: =G16*0.3/100 -> 0 | F46: =(G20)*1/100*12/100 -> 360.00001
B47: Impuesto (base x millar) | C47: 2 | D47: o/oo | E47: 0 | F47: =G20*0.2/100 -> 600.00002
B48: Contrato de cobro | E48: 0 | F48: 0
B49: Liberación del inmueble | E49: 0 | F49: 0
B50: Carta de Pago | E50: 0 | F50: 0
B51: CALCULOS PAGO IMPUESTO DE OPERACIÓN
D52: x | E52: 0
D53: x | E53: 0
B54: Pago de Timbres
B55: Pago a efectuar de Hipoteca a nombre de:
F56: DESCUENTOS DE: | G56: =SUM(G26)+SUM(G31)+SUM(G44) -> 30731.251
A57: ESC. # ___________________ | C57: FECHA: ___________
A58: INV:_______________________ | E58: TOTAL A RECIBIR: | F58: =(G20)-SUM(G56) -> 269268.76
A59: CONTRATO: _______________ | C59: Vo. Bo. ___________Lic.________________________

Sheet Detalle cliente hipotecario
E11: 43790
A13: Solicitante:
A14: Mario Oswaldo Rosales Pur
A16: Préstamo otorgado | C16: ='Detalle hipotecario'!G20 -> 300000.01
A18: Deducciones
A19: 3% mensual 1a.cuota (incluye IVA) | B19: ='Detalle hipotecario'!G26 -> 10080
A20: Royalty 4% | B20: ='Detalle hipotecario'!F31 -> 12000
A21: Gastos Administrativos | B21: ='Detalle hipotecario'!F32+'Detalle hipotecario'!F34 -> 3600.0001
A22: Inscripciones (1o. Y 2do. Lugar, RGPI) | B22: ='Detalle hipotecario'!F36 -> 991.25
A23: Honorarios abogado | B23: ='Detalle hipotecario'!G44 -> 4060.0001 | C23: =SUM(B19:B23) -> 30731.251
A24: Líquido a recibir | C24: =C16-C23 -> 269268.76

Sheet Cálculo RGPI
A3: Base de cálculo Gastos de Registro
A4: 250000 | B4: - Q 10,0000 | C4: =A4-10000 -> 240000 | D4: =+A4/7.89 -> 31685.678
A6: =C4 -> 240000 | B6: x .015% | C6: =+A6*0.15/100 -> 360
A7: (+) Gastos
A8: Inscripción Registro | C8: =160+50 -> 210
A9: Scanner documento | C9: 75
A10: Gastos extraordinarios | C10: 0
C11: =+C10+C9+C8+C6 -> 645
A15: Base de cálculo Gastos de Registro
A16: 50000 | B16: - Q 10,0000 | C16: =A16-10000 -> 40000 | D16: =+A16/7.89 -> 6337.1356
A18: =C16 -> 40000 | B18: x .015% | C18: =+A18*0.15/100 -> 60
A19: (+) Gastos
A20: Inscripción Registro | C20: =160+50 -> 210
A21: Scanner documento | C21: 75
A22: Gastos extraordinarios | C22: 0
C23: =+C22+C21+C20+C18 -> 345
C26: =+C23+C11+(1.25) -> 991.25

Sheet Emision de Cheques
J8: MONEDA | K8: MONTO
A9: FECHA | B9: EMISOR | C9: BANCO | D9: BENEFICIARIO | E9: NO.CUENTA | F9: TIPO | G9: TIPO DE CUENTA | H9: BANCO | I9: CONCEPTO | J9: Q | K9: Q
A10: 45996 | B10: Cube Investments, S.A. | C10: BAM | D10: AUTOMAQ GUATEMALA, S.A. (No Negociable) | E10: 30-2009653-9 | F10: TRASFERENCIA | G10: MONETARIA | H10: BAM | I10: Credito otorgado a Mario Edú Polanco Fores | J10: X | K10: =IF(FORMULARIO!D61="Hipotecario",'Detalle hipotecario'!F58,'Detalle vehiculo'!I52) -> 123300
A11: 45996 | B11: Cube Investments, S.A. | C11: BAM | D11: Cube Investments, S.A. (No Negociable) | F11: TRASFERENCIA | G11: MONETARIA | H11: BAM | I11: Gastos Administrativos, contratos, garantía, visita domiciliar | J11: X | K11: ='Detalle vehiculo'!I50 -> 10605.762
K12: 0
K13: =SUM(K10:K12) -> 133905.76
A19: © CLUB CASH IN . Este documento es propiedad de Club Cash In, copia u otro uso de este documento por y para terceras personas está prohibida.

Sheet  Cotizador cliente
A1: Detalle de cuotas niveladas
A3: Datos del vehículo
B5: Marca: | C5: FOTON | D5: Línea: | E5: AUMARK E | F5: Modelo: | G5: 2026
A7: Nombre: | B7: Mario Edú Polanco Fores | F7: Camion
A9: Valor del vehículo: | C9: 137000
A10: Monto asegurado: | C10: 137000
A11: Enganche: | C11: 13700 | D11: =C11/C9 -> 0.1
A12: Monto a financiar: | C12: =C9-C11 -> 123300 | D12: =(C12/C9) -> 0.9
A14: Plazo (meses): | C14: 60
A15: Tasa de interés: | C15: 0.015
A16: Seguro: | C16: =IF(F7="UBER",VLOOKUP(C10,'Costo seguro'!B2:G782,2,TRUE),IF(F7="Particular",VLOOKUP(C10,'Costo seguro'!B2:G782,2,TRUE),IF(F7="Pick Up",VLOOKUP(C10,'Costo seguro'!B2:G782,3,TRUE),IF(F7="Nuevo",VLOOKUP(C10,'Costo seguro'!B2:G782,2,TRUE),IF(F7="Panel",VLOOKUP(C10,'Costo seguro'!B2:G782,4,TRUE),IF(F7="Camion",VLOOKUP(C10,'Costo seguro'!B2:G782,4,TRUE),IF(F7="Microbus",VLOOKUP(C10,'Costo seguro'!B2:G782,4,TRUE),"")))))))+C20 -> 1194.5624
A17: GPS | C17: 148.2 | E17: Monto total a financiar:
A18: Traspaso | C18: =395+150 -> 545
A19: Gastos administrativos | C19: =C22+D22+E22+F22+G22 -> 10060.762 | E19: Cuota mensual: | F19: =PMT((C15*1.12),C14,-(C12+C18+C19))+C16+C17 -> 4902.3778
A20: Membresía | C20: =VLOOKUP(C10,'Costo seguro'!B2:K782,5,TRUE)-C17 -> 389.0024
B22: =C12+C18+C22+E22+F22+C17+C16 -> 126587.76 | C22: 400 | D22: =ROUNDUP(B22*4%,0) -> 5064 | E22: 400 | F22: 600 | G22: =ROUNDUP(B22*1.78%,0)+C17+C16 -> 3596.7624
B23: Cuota | C23: Saldo inicial | D23: Interés + IVA | E23: Amortización | F23: Saldo final
B24: 0 | C24: =C12+C18+C19 -> 133905.76 | D24: =((C24)*C15*1.12) -> 2249.6168 | E24: 0 | F24: =C24-E24 -> 133905.76
B25: =IF(C25="","",B24+1) -> 1 | C25: =IF(F24<=0.1,"",IF(C24="","",F24)) -> 133905.76 | D25: =IF(C25="","",(C25*$C$15*1.12)) -> 2249.6168 | E25: =IF(D25="","",$F$19-$C$16-$C$17-D25) -> 1309.9986 | F25: =IF(E25="","",C25-E25) -> 132595.76
B26: =IF(C26="","",B25+1) -> 2 | C26: =IF(F25<=0.1,"",IF(C25="","",F25)) -> 132595.76 | D26: =IF(C26="","",(C26*$C$15*1.12)) -> 2227.6088 | E26: =IF(D26="","",$F$19-$C$16-$C$17-D26) -> 1332.0065 | F26: =IF(E26="","",C26-E26) -> 131263.76
B27: =IF(C27="","",B26+1) -> 3 | C27: =IF(F26<=0.1,"",IF(C26="","",F26)) -> 131263.76 | D27: =IF(C27="","",(C27*$C$15*1.12)) -> 2205.2311 | E27: =IF(D27="","",$F$19-$C$16-$C$17-D27) -> 1354.3843 | F27: =IF(E27="","",C27-E27) -> 129909.37
B28: =IF(C28="","",B27+1) -> 4 | C28: =IF(F27<=0.1,"",IF(C27="","",F27)) -> 129909.37 | D28: =IF(C28="","",(C28*$C$15*1.12)) -> 2182.4775 | E28: =IF(D28="","",$F$19-$C$16-$C$17-D28) -> 1377.1379 | F28: =IF(E28="","",C28-E28) -> 128532.24
B29: =IF(C29="","",B28+1) -> 5 | C29: =IF(F28<=0.1,"",IF(C28="","",F28)) -> 128532.24 | D29: =IF(C29="","",(C29*$C$15*1.12)) -> 2159.3415 | E29: =IF(D29="","",$F$19-$C$16-$C$17-D29) -> 1400.2738 | F29: =IF(E29="","",C29-E29) -> 127131.96
B30: =IF(C30="","",B29+1) -> 6 | C30: =IF(F29<=0.1,"",IF(C29="","",F29)) -> 127131.96 | D30: =IF(C30="","",(C30*$C$15*1.12)) -> 2135.8169 | E30: =IF(D30="","",$F$19-$C$16-$C$17-D30) -> 1423.7984 | F30: =IF(E30="","",C30-E30) -> 125708.16
B31: =IF(C31="","",B30+1) -> 7 | C31: =IF(F30<=0.1,"",IF(C30="","",F30)) -> 125708.16 | D31: =IF(C31="","",(C31*$C$15*1.12)) -> 2111.8971 | E31: =IF(D31="","",$F$19-$C$16-$C$17-D31) -> 1447.7182 | F31: =IF(E31="","",C31-E31) -> 124260.44
B32: =IF(C32="","",B31+1) -> 8 | C32: =IF(F31<=0.1,"",IF(C31="","",F31)) -> 124260.44 | D32: =IF(C32="","",(C32*$C$15*1.12)) -> 2087.5755 | E32: =IF(D32="","",$F$19-$C$16-$C$17-D32) -> 1472.0399 | F32: =IF(E32="","",C32-E32) -> 122788.4
B33: =IF(C33="","",B32+1) -> 9 | C33: =IF(F32<=0.1,"",IF(C32="","",F32)) -> 122788.4 | D33: =IF(C33="","",(C33*$C$15*1.12)) -> 2062.8452 | E33: =IF(D33="","",$F$19-$C$16-$C$17-D33) -> 1496.7702 | F33: =IF(E33="","",C33-E33) -> 121291.63
B34: =IF(C34="","",B33+1) -> 10 | C34: =IF(F33<=0.1,"",IF(C33="","",F33)) -> 121291.63 | D34: =IF(C34="","",(C34*$C$15*1.12)) -> 2037.6995 | E34: =IF(D34="","",$F$19-$C$16-$C$17-D34) -> 1521.9159 | F34: =IF(E34="","",C34-E34) -> 119769.72
B35: =IF(C35="","",B34+1) -> 11 | C35: =IF(F34<=0.1,"",IF(C34="","",F34)) -> 119769.72 | D35: =IF(C35="","",(C35*$C$15*1.12)) -> 2012.1313 | E35: =IF(D35="","",$F$19-$C$16-$C$17-D35) -> 1547.4841 | F35: =IF(E35="","",C35-E35) -> 118222.23
B36: =IF(C36="","",B35+1) -> 12 | C36: =IF(F35<=0.1,"",IF(C35="","",F35)) -> 118222.23 | D36: =IF(C36="","",(C36*$C$15*1.12)) -> 1986.1335 | E36: =IF(D36="","",$F$19-$C$16-$C$17-D36) -> 1573.4818 | F36: =IF(E36="","",C36-E36) -> 116648.75
... B135: =IF(C135="","",B134+1) | C135: =IF(F134<=0.1,"",IF(C134="","",F134)) | D135: =IF(C135="","",(C135*$C$15*1.12)) | E135: =IF(D135="","",$F$19-$C$16-$C$17-D135) | F135: =IF(E135="","",C135-E135)

Sheet Cotizador interno
A1: Detalle de cuotas niveladas
A3: Datos del vehículo
B5: Marca: | C5: =' Cotizador cliente'!C5 -> FOTON | D5: Línea: | E5: =' Cotizador cliente'!E5 -> AUMARK E | F5: Modelo: | G5: =' Cotizador cliente'!G5 -> 2026
A7: Nombre: | B7: =' Cotizador cliente'!B7:E7 -> Mario Edú Polanco Fores | G7: =' Cotizador cliente'!F7 -> Camion
A9: Valor del vehículo: | C9: =' Cotizador cliente'!C9 -> 137000
A10: Monto asegurado: | C10: =' Cotizador cliente'!C10 -> 137000
A11: Enganche: | C11: =' Cotizador cliente'!C11 -> 13700 | D11: =C11/C9 -> 0.1
A12: Monto a financiar: | C12: =' Cotizador cliente'!C12 -> 123300 | D12: =(C12/C9) -> 0.9
A14: Plazo (meses): | C14: =' Cotizador cliente'!C14 -> 60
A15: Tasa de interés: | C15: =' Cotizador cliente'!C15 -> 0.015
A16: Seguro: | C16: =IF(G7="UBER",VLOOKUP(C10,'Costo seguro'!B2:G782,2,TRUE),IF(G7="Particular",VLOOKUP(C10,'Costo seguro'!B2:G782,2,TRUE),IF(G7="Pick Up",VLOOKUP(C10,'Costo seguro'!B2:G782,3,TRUE),IF(G7="Nuevo",VLOOKUP(C10,'Costo seguro'!B2:G782,2,TRUE),IF(G7="Panel",VLOOKUP(C10,'Costo seguro'!B2:G782,4,TRUE),IF(G7="Camion",VLOOKUP(C10,'Costo seguro'!B2:G782,4,TRUE),IF(G7="Microbus",VLOOKUP(C10,'Costo seguro'!B2:G782,4,TRUE),""))))))) -> 805.56 | E16: Monto total a financiar:
A17: Traspaso | C17: =' Cotizador cliente'!C18 -> 545
A18: Gastos administrativos | C18: =' Cotizador cliente'!C19 -> 10060.762 | E18: Cuota mensual: | F18: =PMT((C15*1.12),C14,-(C12+C17+C18))+C16+C19 -> 4902.3778
A19: Membresía | C19: =VLOOKUP(C10,'Costo seguro'!B2:K782,5,TRUE) -> 537.2024
B21: Cuota | C21: Saldo inicial | D21: Interés + IVA | E21: Amortización | F21: Saldo final
B22: 1 | C22: =' Cotizador cliente'!C24 -> 133905.76 | D22: =((C22)*C15*1.12) -> 2249.6168 | E22: =$F$18-$C$16-D22-C19 -> 1309.9986 | F22: =C22-E22 -> 132595.76
B23: =IF(C23="","",B22+1) -> 2 | C23: =IF(F22<=0.1,"",IF(C22="","",F22)) -> 132595.76 | D23: =IF(C23="","",(C23*$C$15*1.12)) -> 2227.6088 | E23: =IF(D23="","",$F$18-$C$16-D23-$C$19) -> 1332.0065 | F23: =IF(E23="","",C23-E23) -> 131263.76
B24: =IF(C24="","",B23+1) -> 3 | C24: =IF(F23<=0.1,"",IF(C23="","",F23)) -> 131263.76 | D24: =IF(C24="","",(C24*$C$15*1.12)) -> 2205.2311 | E24: =IF(D24="","",$F$18-$C$16-D24-$C$19) -> 1354.3843 | F24: =IF(E24="","",C24-E24) -> 129909.37
B25: =IF(C25="","",B24+1) -> 4 | C25: =IF(F24<=0.1,"",IF(C24="","",F24)) -> 129909.37 | D25: =IF(C25="","",(C25*$C$15*1.12)) -> 2182.4775 | E25: =IF(D25="","",$F$18-$C$16-D25-$C$19) -> 1377.1379 | F25: =IF(E25="","",C25-E25) -> 128532.24
B26: =IF(C26="","",B25+1) -> 5 | C26: =IF(F25<=0.1,"",IF(C25="","",F25)) -> 128532.24 | D26: =IF(C26="","",(C26*$C$15*1.12)) -> 2159.3415 | E26: =IF(D26="","",$F$18-$C$16-D26-$C$19) -> 1400.2738 | F26: =IF(E26="","",C26-E26) -> 127131.96
B27: =IF(C27="","",B26+1) -> 6 | C27: =IF(F26<=0.1,"",IF(C26="","",F26)) -> 127131.96 | D27: =IF(C27="","",(C27*$C$15*1.12)) -> 2135.8169 | E27: =IF(D27="","",$F$18-$C$16-D27-$C$19) -> 1423.7984 | F27: =IF(E27="","",C27-E27) -> 125708.16
B28: =IF(C28="","",B27+1) -> 7 | C28: =IF(F27<=0.1,"",IF(C27="","",F27)) -> 125708.16 | D28: =IF(C28="","",(C28*$C$15*1.12)) -> 2111.8971 | E28: =IF(D28="","",$F$18-$C$16-D28-$C$19) -> 1447.7182 | F28: =IF(E28="","",C28-E28) -> 124260.44
B29: =IF(C29="","",B28+1) -> 8 | C29: =IF(F28<=0.1,"",IF(C28="","",F28)) -> 124260.44 | D29: =IF(C29="","",(C29*$C$15*1.12)) -> 2087.5755 | E29: =IF(D29="","",$F$18-$C$16-D29-$C$19) -> 1472.0399 | F29: =IF(E29="","",C29-E29) -> 122788.4
B30: =IF(C30="","",B29+1) -> 9 | C30: =IF(F29<=0.1,"",IF(C29="","",F29)) -> 122788.4 | D30: =IF(C30="","",(C30*$C$15*1.12)) -> 2062.8452 | E30: =IF(D30="","",$F$18-$C$16-D30-$C$19) -> 1496.7702 | F30: =IF(E30="","",C30-E30) -> 121291.63
B31: =IF(C31="","",B30+1) -> 10 | C31: =IF(F30<=0.1,"",IF(C30="","",F30)) -> 121291.63 | D31: =IF(C31="","",(C31*$C$15*1.12)) -> 2037.6995 | E31: =IF(D31="","",$F$18-$C$16-D31-$C$19) -> 1521.9159 | F31: =IF(E31="","",C31-E31) -> 119769.72
B32: =IF(C32="","",B31+1) -> 11 | C32: =IF(F31<=0.1,"",IF(C31="","",F31)) -> 119769.72 | D32: =IF(C32="","",(C32*$C$15*1.12)) -> 2012.1313 | E32: =IF(D32="","",$F$18-$C$16-D32-$C$19) -> 1547.4841 | F32: =IF(E32="","",C32-E32) -> 118222.23
B33: =IF(C33="","",B32+1) -> 12 | C33: =IF(F32<=0.1,"",IF(C32="","",F32)) -> 118222.23 | D33: =IF(C33="","",(C33*$C$15*1.12)) -> 1986.1335 | E33: =IF(D33="","",$F$18-$C$16-D33-$C$19) -> 1573.4818 | F33: =IF(E33="","",C33-E33) -> 116648.75
B34: =IF(C34="","",B33+1) -> 13 | C34: =IF(F33<=0.1,"",IF(C33="","",F33)) -> 116648.75 | D34: =IF(C34="","",(C34*$C$15*1.12)) -> 1959.699 | E34: =IF(D34="","",$F$18-$C$16-D34-$C$19) -> 1599.9163 | F34: =IF(E34="","",C34-E34) -> 115048.84
... B133: =IF(C133="","",B132+1) | C133: =IF(F132<=0.1,"",IF(C132="","",F132)) | D133: =IF(C133="","",(C133*$C$15*1.12)) | E133: =IF(D133="","",$F$18-$C$16-D133-$C$19) | F133: =IF(E133="","",C133-E133)
E134: =IF(D134="","",$F$18-$C$16-D134-$C$19)
E135: =IF(D135="","",$F$18-$C$16-D135-$C$19)

Sheet Costo seguro
B1: Precio | C1: INREXSA | D1: Pick Up | E1: Panel, Camion, Microbus | F1: Membresia | I1: INREXSA | J1: Pick Up | K1: Panel, Camion, Microbus | L1: Membresia
B2: 20000 | C2: 245 | D2: 245 | E2: 245 | F2: 329.365 | I2: 260.925 | J2: 260.925 | K2: 260.925 | L2: 313.44
B3: 21000 | C3: 245 | D3: 245 | E3: 245 | F3: 329.365 | I3: 260.925 | J3: 260.925 | K3: 260.925 | L3: 313.44
B4: 22000 | C4: 245 | D4: 245 | E4: 245 | F4: 329.365 | I4: 260.925 | J4: 260.925 | K4: 260.925 | L4: 313.44
B5: 23000 | C5: 245 | D5: 245 | E5: 245 | F5: 329.365 | I5: 260.925 | J5: 260.925 | K5: 260.925 | L5: 313.44
B6: 24000 | C6: 245 | D6: 245 | E6: 245 | F6: 329.365 | I6: 260.925 | J6: 260.925 | K6: 260.925 | L6: 313.44
B7: 25000 | C7: 245 | D7: 245 | E7: 245 | F7: 329.365 | I7: 260.925 | J7: 260.925 | K7: 260.925 | L7: 313.44
B8: 26000 | C8: 245 | D8: 245 | E8: 245 | F8: 329.365 | I8: 260.925 | J8: 260.925 | K8: 260.925 | L8: 313.44
B9: 27000 | C9: 245 | D9: 245 | E9: 245 | F9: 329.365 | I9: 260.925 | J9: 260.925 | K9: 260.925 | L9: 313.44
B10: 28000 | C10: 245 | D10: 245 | E10: 245 | F10: 329.365 | I10: 260.925 | J10: 260.925 | K10: 260.925 | L10: 313.44
B11: 29000 | C11: 245 | D11: 245 | E11: 245 | F11: 329.365 | I11: 260.925 | J11: 260.925 | K11: 260.925 | L11: 313.44
B12: 30000 | C12: 245 | D12: 245 | E12: 245 | F12: 329.365 | I12: 260.925 | J12: 260.925 | K12: 260.925 | L12: 313.44
B13: 31000 | C13: 245 | D13: 245 | E13: 245 | F13: 329.365 | I13: 260.925 | J13: 260.925 | K13: 260.925 | L13: 313.44
... B782: 800000 | C782: 2156 | D782: 2399.04 | E782: 4704 | F782: 2339.7931 | I782: 2296.14 | J782: 2554.9776 | K782: 5009.76 | L782: 2034.0331

Sheet Costo seguro (2)
B1: Precio | C1: Precio antiguo | D1: Precio nuevo | E1: UBER | F1: Nuevo - Viejo | G1: Nuevo - Nuevo | H1: Bus hasta 20 pasajeros | I1: Bus 21-35 pasajeros | J1: Bus mas de 35 pasajeros | K1: Membresia parcial usados | L1: Membresia total usados | M1: Membresia parcial nuevos | N1: Membresia total nuevos | O1: Membresía | P1: 0.15
B2: 1 | C2: 276.43 | D2: 225.4 | E2: =C2 -> 276.43 | F2: 362.99 | G2: 300.96 | H2: 486.64 | I2: 561.64 | J2: 711.64 | K2: =L2-(C2-D2)-10.2 -> 133.81 | L2: =(D2*$P$1)+(C2-D2)+10.2+100 -> 195.04 | M2: =N2-(F2-G2)-10.2 -> 122.81 | N2: =L2 -> 195.04
B3: 1000 | C3: 276.43 | D3: 225.4 | E3: =C3 -> 276.43 | F3: 362.99 | G3: 300.96 | H3: 486.64 | I3: 561.64 | J3: 711.64 | K3: =L3-(C3-D3)-10.2 -> 133.81 | L3: =(D3*$P$1)+(C3-D3)+10.2+100 -> 195.04 | M3: =N3-(F3-G3)-10.2 -> 122.81 | N3: =L3 -> 195.04
B4: 5000 | C4: 276.43 | D4: 225.4 | E4: =C4 -> 276.43 | F4: 362.99 | G4: 300.96 | H4: 486.64 | I4: 561.64 | J4: 711.64 | K4: =L4-(C4-D4)-10.2 -> 133.81 | L4: =(D4*$P$1)+(C4-D4)+10.2+100 -> 195.04 | M4: =N4-(F4-G4)-10.2 -> 122.81 | N4: =L4 -> 195.04
B5: 10000 | C5: 276.43 | D5: 225.4 | E5: =C5 -> 276.43 | F5: 362.99 | G5: 300.96 | H5: 486.64 | I5: 561.64 | J5: 711.64 | K5: =L5-(C5-D5)-10.2 -> 133.81 | L5: =(D5*$P$1)+(C5-D5)+10.2+100 -> 195.04 | M5: =N5-(F5-G5)-10.2 -> 122.81 | N5: =L5 -> 195.04
B6: 15000 | C6: 276.43 | D6: 225.4 | E6: =C6 -> 276.43 | F6: 362.99 | G6: 300.96 | H6: 486.64 | I6: 561.64 | J6: 711.64 | K6: =L6-(C6-D6)-10.2 -> 133.81 | L6: =(D6*$P$1)+(C6-D6)+10.2+100 -> 195.04 | M6: =N6-(F6-G6)-10.2 -> 122.81 | N6: =L6 -> 195.04
B7: 20000 | C7: 276.43 | D7: 225.4 | E7: =C7 -> 276.43 | F7: 362.99 | G7: 300.96 | H7: 486.64 | I7: 561.64 | J7: 711.64 | K7: =L7-(C7-D7)-10.2 -> 133.81 | L7: =(D7*$P$1)+(C7-D7)+10.2+100 -> 195.04 | M7: =N7-(F7-G7)-10.2 -> 122.81 | N7: =L7 -> 195.04
B8: 25000 | C8: 276.43 | D8: 225.4 | E8: =C8 -> 276.43 | F8: 362.99 | G8: 300.96 | H8: 486.64 | I8: 561.64 | J8: 711.64 | K8: =L8-(C8-D8)-10.2 -> 133.81 | L8: =(D8*$P$1)+(C8-D8)+10.2+100 -> 195.04 | M8: =N8-(F8-G8)-10.2 -> 122.81 | N8: =L8 -> 195.04
B9: 30000 | C9: 276.43 | D9: 225.4 | E9: =C9 -> 276.43 | F9: 362.99 | G9: 300.96 | H9: 486.64 | I9: 561.64 | J9: 711.64 | K9: =L9-(C9-D9)-10.2 -> 133.81 | L9: =(D9*$P$1)+(C9-D9)+10.2+100 -> 195.04 | M9: =N9-(F9-G9)-10.2 -> 122.81 | N9: =L9 -> 195.04
B10: 35000 | C10: 276.43 | D10: 225.4 | E10: =C10 -> 276.43 | F10: 362.99 | G10: 300.96 | H10: 486.64 | I10: 561.64 | J10: 711.64 | K10: =L10-(C10-D10)-10.2 -> 133.81 | L10: =(D10*$P$1)+(C10-D10)+10.2+100 -> 195.04 | M10: =N10-(F10-G10)-10.2 -> 122.81 | N10: =L10 -> 195.04
B11: 40000 | C11: 302.75 | D11: 225.4 | E11: =C11 -> 302.75 | F11: 362.99 | G11: 300.96 | H11: 486.64 | I11: 561.64 | J11: 711.64 | K11: =L11-(C11-D11)-10.2 -> 151.64 | L11: =139.19+100 -> 239.19 | M11: =N11-(F11-G11)-10.2 -> 166.96 | N11: =L11 -> 239.19
B12: 45000 | C12: 320.55 | D12: 225.4 | E12: =C12 -> 320.55 | F12: 362.99 | G12: 300.96 | H12: 510.16 | I12: 585.16 | J12: 735.16 | K12: =L12-(C12-D12)-10.2 -> 133.84 | L12: =139.19+100 -> 239.19 | M12: =N12-(F12-G12)-10.2 -> 166.96 | N12: =L12 -> 239.19
B13: 50000 | C13: 338.35 | D13: 267.54 | E13: =C13 -> 338.35 | F13: 362.99 | G13: 300.96 | H13: 533.68 | I13: 608.68 | J13: 758.68 | K13: =L13-(C13-D13)-10.2 -> 158.18 | L13: =139.19+100 -> 239.19 | M13: =N13-(F13-G13)-10.2 -> 166.96 | N13: =L13 -> 239.19
B14: 55000 | C14: 356.15 | D14: 281.06 | E14: =C14 -> 356.15 | F14: 362.99 | G14: 300.96 | H14: 557.2 | I14: 632.2 | J14: 782.2 | K14: =L14-(C14-D14)-10.2 -> 153.9 | L14: =139.19+100 -> 239.19 | M14: =N14-(F14-G14)-10.2 -> 166.96 | N14: =L14 -> 239.19
B15: 60000 | C15: 373.95 | D15: 302.56 | E15: =C15 -> 373.95 | F15: 362.99 | G15: 300.96 | H15: 580.72 | I15: 655.72 | J15: 805.72 | K15: =L15-(C15-D15)-10.2 -> 157.6 | L15: =139.19+100 -> 239.19 | M15: =N15-(F15-G15)-10.2 -> 166.96 | N15: =L15 -> 239.19
B16: 65000 | C16: 391.76 | D16: 316.45 | E16: =C16 -> 391.76 | F16: 362.99 | G16: 300.96 | H16: 604.24 | I16: 679.24 | J16: 829.24 | K16: =L16-(C16-D16)-10.2 -> 153.68 | L16: =139.19+100 -> 239.19 | M16: =N16-(F16-G16)-10.2 -> 166.96 | N16: =L16 -> 239.19
B17: 70000 | C17: 409.56 | D17: 362.9 | E17: =C17 -> 409.56 | F17: 362.99 | G17: 300.96 | H17: 627.76 | I17: 702.76 | J17: 852.76 | K17: =L17-(C17-D17)-10.2 -> 182.33 | L17: =139.19+100 -> 239.19 | M17: =N17-(F17-G17)-10.2 -> 166.96 | N17: =L17 -> 239.19
B18: 75000 | C18: 427.36 | D18: 378.16 | E18: =C18 -> 427.36 | F18: 378.77 | G18: 313.36 | H18: 651.28 | I18: 726.28 | J18: 876.28 | K18: =L18-(C18-D18)-10.2 -> 179.79 | L18: =139.19+100 -> 239.19 | M18: =N18-(F18-G18)-10.2 -> 163.58 | N18: =L18 -> 239.19
B19: 80000 | C19: 445.16 | D19: 393.42 | E19: =C19 -> 445.16 | F19: 394.55 | G19: 325.75 | H19: 674.8 | I19: 749.8 | J19: 899.8 | K19: =L19-(C19-D19)-10.2 -> 177.25 | L19: =139.19+100 -> 239.19 | M19: =N19-(F19-G19)-10.2 -> 160.19 | N19: =L19 -> 239.19
B20: 85000 | C20: 462.96 | D20: 408.67 | E20: =C20 -> 462.96 | F20: 462.96 | G20: 381.53 | H20: 698.32 | I20: 773.32 | J20: 923.32 | K20: =L20-(C20-D20)-10.2 -> 174.7 | L20: =139.19+100 -> 239.19 | M20: =N20-(F20-G20)-10.2 -> 147.56 | N20: =L20 -> 239.19
B21: 90000 | C21: 480.77 | D21: 423.93 | E21: =C21 -> 480.77 | F21: 480.77 | G21: 395.52 | H21: 721.84 | I21: 796.84 | J21: 946.84 | K21: =L21-(C21-D21)-10.2 -> 172.15 | L21: =139.19+100 -> 239.19 | M21: =N21-(F21-G21)-10.2 -> 143.74 | N21: =L21 -> 239.19
B22: 95000 | C22: 498.57 | D22: 439.19 | E22: =C22 -> 498.57 | F22: 498.57 | G22: 409.5 | H22: 745.36 | I22: 820.36 | J22: 970.36 | K22: =L22-(C22-D22)-10.2 -> 169.61 | L22: =139.19+100 -> 239.19 | M22: =N22-(F22-G22)-10.2 -> 139.92 | N22: =L22 -> 239.19
B23: 100000 | C23: 516.37 | D23: 387 | E23: =C23 -> 516.37 | F23: 387 | G23: 359.36 | H23: 768.88 | I23: 843.88 | J23: 993.88 | K23: =L23-(C23-D23)-10.2 -> 158.05 | L23: 297.62 | M23: =N23-(F23-G23)-10.2 -> 259.78 | N23: =L23 -> 297.62
B24: 105000 | C24: 485.41 | D24: 399.16 | E24: =C24 -> 485.41 | F24: 399.16 | G24: 370.42 | H24: 792.4 | I24: 867.4 | J24: 1017.4 | K24: =L24-(C24-D24)-10.2 -> 201.17 | L24: 297.62 | M24: =N24-(F24-G24)-10.2 -> 258.68 | N24: =L24 -> 297.62
B25: 110000 | C25: 500.89 | D25: 411.33 | E25: =C25 -> 500.89 | F25: 411.33 | G25: 381.47 | H25: 815.92 | I25: 890.92 | J25: 1040.92 | K25: =L25-(C25-D25)-10.2 -> 197.86 | L25: 297.62 | M25: =N25-(F25-G25)-10.2 -> 257.56 | N25: =L25 -> 297.62
B26: 115000 | C26: 516.37 | D26: 423.49 | E26: =C26 -> 516.37 | F26: 423.49 | G26: 392.53 | H26: 839.44 | I26: 914.44 | J26: 1064.44 | K26: =L26-(C26-D26)-10.2 -> 194.54 | L26: 297.62 | M26: =N26-(F26-G26)-10.2 -> 256.46 | N26: =L26 -> 297.62
B27: 120000 | C27: 531.85 | D27: 435.65 | E27: =C27 -> 531.85 | F27: 435.65 | G27: 403.59 | H27: 862.96 | I27: 937.96 | J27: 1087.96 | K27: =L27-(C27-D27)-10.2 -> 191.22 | L27: 297.62 | M27: =N27-(F27-G27)-10.2 -> 255.36 | N27: =L27 -> 297.62
B28: 125000 | C28: 547.33 | D28: 447.82 | E28: =C28 -> 547.33 | F28: 447.82 | G28: 414.65 | H28: 886.48 | I28: 961.48 | J28: 1111.48 | K28: =L28-(C28-D28)-10.2 -> 187.91 | L28: 297.62 | M28: =N28-(F28-G28)-10.2 -> 254.25 | N28: =L28 -> 297.62
B29: 130000 | C29: 562.81 | D29: 459.98 | E29: =C29 -> 562.81 | F29: 459.98 | G29: 425.7 | H29: 910 | I29: 985 | J29: 1135 | K29: =L29-(C29-D29)-10.2 -> 184.59 | L29: 297.62 | M29: =N29-(F29-G29)-10.2 -> 253.14 | N29: =L29 -> 297.62
B30: 135000 | C30: 578.29 | D30: 472.14 | E30: =C30 -> 578.29 | F30: 472.14 | G30: 436.76 | H30: 933.52 | I30: 1008.52 | J30: 1158.52 | K30: =L30-(C30-D30)-10.2 -> 181.27 | L30: 297.62 | M30: =N30-(F30-G30)-10.2 -> 252.04 | N30: =L30 -> 297.62
B31: 140000 | C31: 593.77 | D31: 484.31 | E31: =C31 -> 593.77 | F31: 484.31 | G31: 447.82 | H31: 957.04 | I31: 1032.04 | J31: 1182.04 | K31: =L31-(C31-D31)-10.2 -> 177.96 | L31: 297.62 | M31: =N31-(F31-G31)-10.2 -> 250.93 | N31: =L31 -> 297.62
B32: 145000 | C32: 571.66 | D32: 496.47 | E32: =C32 -> 571.66 | F32: 496.47 | G32: 458.87 | H32: 980.56 | I32: 1055.56 | J32: 1205.56 | K32: =L32-(C32-D32)-10.2 -> 212.23 | L32: 297.62 | M32: =N32-(F32-G32)-10.2 -> 249.82 | N32: =L32 -> 297.62
B33: 150000 | C33: 586.03 | D33: 508.63 | E33: =C33 -> 586.03 | F33: 508.63 | G33: 469.93 | H33: 1004.08 | I33: 1079.08 | J33: 1229.08 | K33: =L33-(C33-D33)-10.2 -> 210.02 | L33: 297.62 | M33: =N33-(F33-G33)-10.2 -> 248.72 | N33: =L33 -> 297.62
B34: 155000 | C34: 600.41 | D34: 520.79 | E34: =C34 -> 600.41 | F34: 520.79 | G34: 480.99 | H34: 1027.6 | I34: 1102.6 | J34: 1252.6 | K34: =L34-(C34-D34)-10.2 -> 207.8 | L34: 297.62 | M34: =N34-(F34-G34)-10.2 -> 247.62 | N34: =L34 -> 297.62
... B41: 190000 | C41: 701.03 | D41: 605.93 | E41: =C41 -> 701.03 | F41: 605.93 | G41: 558.39 | H41: 1192.24 | I41: 1267.24 | J41: 1417.24 | K41: =L41-(C41-D41)-10.2 -> 192.32 | L41: 297.62 | M41: =N41-(F41-G41)-10.2 -> 239.88 | N41: =L41 -> 297.62
B42: 195000 | C42: 715.4 | D42: 618.1 | E42: =C42 -> 715.4 | F42: 618.1 | G42: 569.45 | H42: 1215.76 | I42: 1290.76 | J42: 1440.76 | K42: =L42-(C42-D42)-10.2 -> 192.715 | L42: =(D42*$P$1)+(C42-D42)+10.2+100 -> 300.215 | M42: =N42-(F42-G42)-10.2 -> 241.365 | N42: =L42 -> 300.215
B43: 200000 | C43: 729.78 | D43: 630.26 | E43: =C43 -> 729.78 | F43: 630.26 | G43: 580.5 | H43: 1239.28 | I43: 1314.28 | J43: 1464.28 | K43: =L43-(C43-D43)-10.2 -> 194.539 | L43: =(D43*$P$1)+(C43-D43)+10.2+100 -> 304.259 | M43: =N43-(F43-G43)-10.2 -> 244.299 | N43: =L43 -> 304.259
B44: 205000 | C44: 744.15 | D44: 642.42 | E44: =C44 -> 744.15 | F44: 642.42 | G44: 591.56 | H44: 1262.8 | I44: 1337.8 | J44: 1487.8 | K44: =L44-(C44-D44)-10.2 -> 196.363 | L44: =(D44*$P$1)+(C44-D44)+10.2+100 -> 308.293 | M44: =N44-(F44-G44)-10.2 -> 247.233 | N44: =L44 -> 308.293
B45: 210000 | C45: 758.52 | D45: 654.59 | E45: =C45 -> 758.52 | F45: 654.59 | G45: 602.62 | H45: 1286.32 | I45: 1361.32 | J45: 1511.32 | K45: =L45-(C45-D45)-10.2 -> 198.1885 | L45: =(D45*$P$1)+(C45-D45)+10.2+100 -> 312.3185 | M45: =N45-(F45-G45)-10.2 -> 250.1485 | N45: =L45 -> 312.3185
B46: 215000 | C46: 772.9 | D46: 666.75 | E46: =C46 -> 772.9 | F46: 666.75 | G46: 613.67 | H46: 1309.84 | I46: 1384.84 | J46: 1534.84 | K46: =L46-(C46-D46)-10.2 -> 200.0125 | L46: =(D46*$P$1)+(C46-D46)+10.2+100 -> 316.3625 | M46: =N46-(F46-G46)-10.2 -> 253.0825 | N46: =L46 -> 316.3625
B47: 220000 | C47: 787.27 | D47: 678.91 | E47: =C47 -> 787.27 | F47: 678.91 | G47: 624.73 | H47: 1333.36 | I47: 1408.36 | J47: 1558.36 | K47: =L47-(C47-D47)-10.2 -> 201.8365 | L47: =(D47*$P$1)+(C47-D47)+10.2+100 -> 320.3965 | M47: =N47-(F47-G47)-10.2 -> 256.0165 | N47: =L47 -> 320.3965
B48: 225000 | C48: 801.65 | D48: 691.08 | E48: =C48 -> 801.65 | F48: 691.08 | G48: 635.79 | H48: 1356.88 | I48: 1431.88 | J48: 1581.88 | K48: =L48-(C48-D48)-10.2 -> 203.662 | L48: =(D48*$P$1)+(C48-D48)+10.2+100 -> 324.432 | M48: =N48-(F48-G48)-10.2 -> 258.942 | N48: =L48 -> 324.432
B49: 230000 | C49: 816.02 | D49: 703.24 | E49: =C49 -> 816.02 | F49: 703.24 | G49: 646.85 | H49: 1380.4 | I49: 1455.4 | J49: 1605.4 | K49: =L49-(C49-D49)-10.2 -> 205.486 | L49: =(D49*$P$1)+(C49-D49)+10.2+100 -> 328.466 | M49: =N49-(F49-G49)-10.2 -> 261.876 | N49: =L49 -> 328.466
B50: 235000 | C50: 830.4 | D50: 715.4 | E50: =C50 -> 830.4 | F50: 715.4 | G50: 657.9 | H50: 1403.92 | I50: 1478.92 | J50: 1628.92 | K50: =L50-(C50-D50)-10.2 -> 207.31 | L50: =(D50*$P$1)+(C50-D50)+10.2+100 -> 332.51 | M50: =N50-(F50-G50)-10.2 -> 264.81 | N50: =L50 -> 332.51
B51: 240000 | C51: 844.77 | D51: 727.56 | E51: =C51 -> 844.77 | F51: 727.56 | G51: 668.96 | H51: 1427.44 | I51: 1502.44 | J51: 1652.44 | K51: =L51-(C51-D51)-10.2 -> 209.134 | L51: =(D51*$P$1)+(C51-D51)+10.2+100 -> 336.544 | M51: =N51-(F51-G51)-10.2 -> 267.744 | N51: =L51 -> 336.544
B52: 245000 | C52: 859.14 | D52: 739.73 | E52: =C52 -> 859.14 | F52: 739.73 | G52: 680.02 | H52: 1450.96 | I52: 1525.96 | J52: 1675.96 | K52: =L52-(C52-D52)-10.2 -> 210.9595 | L52: =(D52*$P$1)+(C52-D52)+10.2+100 -> 340.5695 | M52: =N52-(F52-G52)-10.2 -> 270.6595 | N52: =L52 -> 340.5695
B53: 250000 | C53: 873.52 | D53: 751.89 | E53: =C53 -> 873.52 | F53: 751.89 | G53: 691.08 | H53: 1474.48 | I53: 1549.48 | J53: 1699.48 | K53: =L53-(C53-D53)-10.2 -> 212.7835 | L53: =(D53*$P$1)+(C53-D53)+10.2+100 -> 344.6135 | M53: =N53-(F53-G53)-10.2 -> 273.6035 | N53: =L53 -> 344.6135
... B63: 300000 | C63: 1017.26 | D63: 873.52 | E63: =C63 -> 1017.26 | F63: 873.52 | G63: 801.65 | H63: 1709.68 | I63: 1784.68 | J63: 1934.68 | K63: =L63-(C63-D63)-10.2 -> 231.028 | L63: =(D63*$P$1)+(C63-D63)+10.2+100 -> 384.968 | M63: =N63-(F63-G63)-10.2 -> 302.898 | N63: =L63 -> 384.968
B64: 305000 | C64: 1031.64 | D64: 885.68 | E64: =C64 -> 1031.64 | F64: 885.68 | G64: 812.7 | K64: =L64-(C64-D64)-10.2 -> 232.852 | L64: =(D64*$P$1)+(C64-D64)+10.2+100 -> 389.012 | M64: =N64-(F64-G64)-10.2 -> 305.832 | N64: =L64 -> 389.012
B65: 310000 | C65: 1046.01 | D65: 897.84 | E65: =C65 -> 1046.01 | F65: 897.84 | G65: 823.76 | K65: =L65-(C65-D65)-10.2 -> 234.676 | L65: =(D65*$P$1)+(C65-D65)+10.2+100 -> 393.046 | M65: =N65-(F65-G65)-10.2 -> 308.766 | N65: =L65 -> 393.046
B66: 315000 | C66: 1060.39 | D66: 910.01 | E66: =C66 -> 1060.39 | F66: 910.01 | G66: 834.82 | K66: =L66-(C66-D66)-10.2 -> 236.5015 | L66: =(D66*$P$1)+(C66-D66)+10.2+100 -> 397.0815 | M66: =N66-(F66-G66)-10.2 -> 311.6915 | N66: =L66 -> 397.0815
B67: 320000 | C67: 1074.76 | D67: 922.17 | E67: =C67 -> 1074.76 | F67: 922.17 | G67: 845.88 | K67: =L67-(C67-D67)-10.2 -> 238.3255 | L67: =(D67*$P$1)+(C67-D67)+10.2+100 -> 401.1155 | M67: =N67-(F67-G67)-10.2 -> 314.6255 | N67: =L67 -> 401.1155
B68: 325000 | C68: 1089.13 | D68: 934.33 | E68: =C68 -> 1089.13 | F68: 934.33 | G68: 856.93 | K68: =L68-(C68-D68)-10.2 -> 240.1495 | L68: =(D68*$P$1)+(C68-D68)+10.2+100 -> 405.1495 | M68: =N68-(F68-G68)-10.2 -> 317.5495 | N68: =L68 -> 405.1495
B69: 330000 | C69: 1103.51 | D69: 946.5 | E69: =C69 -> 1103.51 | F69: 946.5 | G69: 867.99 | K69: =L69-(C69-D69)-10.2 -> 241.975 | L69: =(D69*$P$1)+(C69-D69)+10.2+100 -> 409.185 | M69: =N69-(F69-G69)-10.2 -> 320.475 | N69: =L69 -> 409.185
B70: 335000 | C70: 1117.88 | D70: 958.66 | E70: =C70 -> 1117.88 | F70: 958.66 | G70: 879.05 | K70: =L70-(C70-D70)-10.2 -> 243.799 | L70: =(D70*$P$1)+(C70-D70)+10.2+100 -> 413.219 | M70: =N70-(F70-G70)-10.2 -> 323.409 | N70: =L70 -> 413.219
B71: 340000 | C71: 1132.26 | D71: 970.82 | E71: =C71 -> 1132.26 | F71: 970.82 | G71: 890.1 | K71: =L71-(C71-D71)-10.2 -> 245.623 | L71: =(D71*$P$1)+(C71-D71)+10.2+100 -> 417.263 | M71: =N71-(F71-G71)-10.2 -> 326.343 | N71: =L71 -> 417.263
B72: 345000 | C72: 1146.63 | D72: 982.99 | E72: =C72 -> 1146.63 | F72: 982.99 | G72: 901.16 | K72: =L72-(C72-D72)-10.2 -> 247.4485 | L72: =(D72*$P$1)+(C72-D72)+10.2+100 -> 421.2885 | M72: =N72-(F72-G72)-10.2 -> 329.2585 | N72: =L72 -> 421.2885
B73: 350000 | C73: 1161.01 | D73: 995.15 | E73: =C73 -> 1161.01 | F73: 995.15 | G73: 912.22 | K73: =L73-(C73-D73)-10.2 -> 249.2725 | L73: =(D73*$P$1)+(C73-D73)+10.2+100 -> 425.3325 | M73: =N73-(F73-G73)-10.2 -> 332.2025 | N73: =L73 -> 425.3325
B74: 355000 | C74: 1175.38 | D74: 1007.31 | E74: =C74 -> 1175.38 | F74: 1007.31 | G74: 923.28 | K74: =L74-(C74-D74)-10.2 -> 251.0965 | L74: =(D74*$P$1)+(C74-D74)+10.2+100 -> 429.3665 | M74: =N74-(F74-G74)-10.2 -> 335.1365 | N74: =L74 -> 429.3665
B75: 360000 | C75: 1189.75 | D75: 1019.47 | E75: =C75 -> 1189.75 | F75: 1019.47 | G75: 934.33 | K75: =L75-(C75-D75)-10.2 -> 252.9205 | L75: =(D75*$P$1)+(C75-D75)+10.2+100 -> 433.4005 | M75: =N75-(F75-G75)-10.2 -> 338.0605 | N75: =L75 -> 433.4005
... B103: 500000 | C103: 1592.24 | D103: 1360.04 | E103: =C103 -> 1592.24 | F103: 1360.04 | G103: 1243.94 | K103: =L103-(C103-D103)-10.2 -> 304.006 | L103: =(D103*$P$1)+(C103-D103)+10.2+100 -> 546.406 | M103: =N103-(F103-G103)-10.2 -> 420.106 | N103: =L103 -> 546.406

Sheet Cuotas niveladas
B10: Nombre:
B11: Monto solicitado | J11: 60000
B12: Tasa de interés | J12: 0.0175 | M12: =(J12*1.12) -> 0.0196
B13: Plazo (Meses) | J13: 60
B14: Seguro | J14: 0
B15: GPS | J15: 0
B16: Cuota | J16: =IFERROR(PMT(M12,J13,-J11),0) -> 1709.4019
A18: Mes | B18: Fecha de pago | C18: Saldo inicial | F18: Intereses | H18: IVA | J18: Interés + IVA | L18: Cuota | O18: Amortización | R18: Seguro | S18: GPS | T18: Saldo final | W18: Cuota mensual
B22: 44342 | C22: =J11 -> 60000 | F22: =C22*$J$12 -> 1050 | H22: =F22*0.12 -> 126 | J22: =F22+H22 -> 1176 | L22: =$J$16 -> 1709.4019 | O22: =L22-J22 -> 533.40193 | R22: =IF(C22="","",$J$14) -> 0 | S22: =IF(C22="","",$J$15) -> 0 | T22: =C22-O22 -> 59466.598 | W22: =IFERROR(L22+R22+S22,"") -> 1709.4019
A23: 1 | B23: =IF(C23="","",EDATE($B$22,A23)) -> 44373 | C23: =IF(C22="","",T22) -> 59466.598 | F23: =C23*$J$12 -> 1040.6655 | H23: =F23*0.12 -> 124.87986 | J23: =F23+H23 -> 1165.5453 | L23: =$J$16 -> 1709.4019 | O23: =L23-J23 -> 543.85661 | R23: =IF(C23="","",$J$14) -> 0 | S23: =IF(C23="","",$J$15) -> 0 | T23: =C23-O23 -> 58922.741 | W23: =IF(C23="","",$W$22) -> 1709.4019
A24: 2 | B24: =IF(C24="","",EDATE($B$22,A24)) -> 44403 | C24: =IF(C23="","",T23) -> 58922.741 | F24: =C24*$J$12 -> 1031.148 | H24: =F24*0.12 -> 123.73776 | J24: =F24+H24 -> 1154.8857 | L24: =$J$16 -> 1709.4019 | O24: =L24-J24 -> 554.5162 | R24: =IF(C24="","",$J$14) -> 0 | S24: =IF(C24="","",$J$15) -> 0 | T24: =C24-O24 -> 58368.225 | W24: =IF(C24="","",$W$22) -> 1709.4019
A25: 3 | B25: =IF(C25="","",EDATE($B$22,A25)) -> 44434 | C25: =IF(C24="","",T24) -> 58368.225 | F25: =C25*$J$12 -> 1021.4439 | H25: =F25*0.12 -> 122.57327 | J25: =F25+H25 -> 1144.0172 | L25: =$J$16 -> 1709.4019 | O25: =L25-J25 -> 565.38471 | R25: =IF(C25="","",$J$14) -> 0 | S25: =IF(C25="","",$J$15) -> 0 | T25: =C25-O25 -> 57802.841 | W25: =IF(C25="","",$W$22) -> 1709.4019
A26: 4 | B26: =IF(C26="","",EDATE($B$22,A26)) -> 44465 | C26: =IF(C25="","",T25) -> 57802.841 | F26: =C26*$J$12 -> 1011.5497 | H26: =F26*0.12 -> 121.38597 | J26: =F26+H26 -> 1132.9357 | L26: =$J$16 -> 1709.4019 | O26: =L26-J26 -> 576.46625 | R26: =IF(C26="","",$J$14) -> 0 | S26: =IF(C26="","",$J$15) -> 0 | T26: =C26-O26 -> 57226.374 | W26: =IF(C26="","",$W$22) -> 1709.4019
A27: 5 | B27: =IF(C27="","",EDATE($B$22,A27)) -> 44495 | C27: =IF(C26="","",T26) -> 57226.374 | F27: =C27*$J$12 -> 1001.4616 | H27: =F27*0.12 -> 120.17539 | J27: =IF(F27="","",F27+H27) -> 1121.6369 | L27: =$J$16 -> 1709.4019 | O27: =L27-J27 -> 587.76499 | R27: =IF(C27="","",$J$14) -> 0 | S27: =IF(C27="","",$J$15) -> 0 | T27: =C27-O27 -> 56638.609 | W27: =IF(C27="","",$W$22) -> 1709.4019
A28: 6 | B28: =IF(C28="","",EDATE($B$22,A28)) -> 44526 | C28: =IF(T27<=0.1,"",T27) -> 56638.609 | F28: =IF(C28="","",(C28*$J$12)) -> 991.17566 | H28: =IF(F28="","",(F28*0.12)) -> 118.94108 | J28: =IF(F28="","",F28+H28) -> 1110.1167 | L28: =IF(C28="","",$J$16) -> 1709.4019 | O28: =IF(C28="","",L28-J28) -> 599.28519 | R28: =IF(C28="","",$J$14) -> 0 | S28: =IF(C28="","",$J$15) -> 0 | T28: =IF(C28="","",C28-O28) -> 56039.324 | W28: =IF(C28="","",$W$22) -> 1709.4019
A29: 7 | B29: =IF(C29="","",EDATE($B$22,A29)) -> 44556 | C29: =IF(T28<=0.1,"",T28) -> 56039.324 | F29: =IF(C29="","",(C29*$J$12)) -> 980.68817 | H29: =IF(F29="","",(F29*0.12)) -> 117.68258 | J29: =IF(F29="","",F29+H29) -> 1098.3708 | L29: =IF(H29="","",$J$16) -> 1709.4019 | O29: =IF(C29="","",L29-J29) -> 611.03118 | R29: =IF(C29="","",$J$14) -> 0 | S29: =IF(C29="","",$J$15) -> 0 | T29: =IF(C29="","",C29-O29) -> 55428.293 | W29: =IF(C29="","",$W$22) -> 1709.4019
A30: 8 | B30: =IF(C30="","",EDATE($B$22,A30)) -> 44587 | C30: =IF(T29<=0.1,"",T29) -> 55428.293 | F30: =IF(C30="","",(C30*$J$12)) -> 969.99513 | H30: =IF(F30="","",(F30*0.12)) -> 116.39942 | J30: =IF(F30="","",F30+H30) -> 1086.3945 | L30: =IF(H30="","",$J$16) -> 1709.4019 | O30: =IF(C30="","",L30-J30) -> 623.00739 | R30: =IF(C30="","",$J$14) -> 0 | S30: =IF(C30="","",$J$15) -> 0 | T30: =IF(C30="","",C30-O30) -> 54805.286 | W30: =IF(C30="","",$W$22) -> 1709.4019
A31: 9 | B31: =IF(C31="","",EDATE($B$22,A31)) -> 44618 | C31: =IF(T30<=0.1,"",T30) -> 54805.286 | F31: =IF(C31="","",(C31*$J$12)) -> 959.0925 | H31: =IF(F31="","",(F31*0.12)) -> 115.0911 | J31: =IF(F31="","",F31+H31) -> 1074.1836 | L31: =IF(H31="","",$J$16) -> 1709.4019 | O31: =IF(C31="","",L31-J31) -> 635.21833 | R31: =IF(C31="","",$J$14) -> 0 | S31: =IF(C31="","",$J$15) -> 0 | T31: =IF(C31="","",C31-O31) -> 54170.067 | W31: =IF(C31="","",$W$22) -> 1709.4019
A32: 10 | B32: =IF(C32="","",EDATE($B$22,A32)) -> 44646 | C32: =IF(T31<=0.1,"",T31) -> 54170.067 | F32: =IF(C32="","",(C32*$J$12)) -> 947.97618 | H32: =IF(F32="","",(F32*0.12)) -> 113.75714 | J32: =IF(F32="","",F32+H32) -> 1061.7333 | L32: =IF(H32="","",$J$16) -> 1709.4019 | O32: =IF(C32="","",L32-J32) -> 647.66861 | R32: =IF(C32="","",$J$14) -> 0 | S32: =IF(C32="","",$J$15) -> 0 | T32: =IF(C32="","",C32-O32) -> 53522.399 | W32: =IF(C32="","",$W$22) -> 1709.4019
A33: 11 | B33: =IF(C33="","",EDATE($B$22,A33)) -> 44677 | C33: =IF(T32<=0.1,"",T32) -> 53522.399 | F33: =IF(C33="","",(C33*$J$12)) -> 936.64198 | H33: =IF(F33="","",(F33*0.12)) -> 112.39704 | J33: =IF(F33="","",F33+H33) -> 1049.039 | L33: =IF(H33="","",$J$16) -> 1709.4019 | O33: =IF(C33="","",L33-J33) -> 660.36292 | R33: =IF(C33="","",$J$14) -> 0 | S33: =IF(C33="","",$J$15) -> 0 | T33: =IF(C33="","",C33-O33) -> 52862.036 | W33: =IF(C33="","",$W$22) -> 1709.4019
A34: 12 | B34: =IF(C34="","",EDATE($B$22,A34)) -> 44707 | C34: =IF(T33<=0.1,"",T33) -> 52862.036 | F34: =IF(C34="","",(C34*$J$12)) -> 925.08562 | H34: =IF(F34="","",(F34*0.12)) -> 111.01027 | J34: =IF(F34="","",F34+H34) -> 1036.0959 | L34: =IF(H34="","",$J$16) -> 1709.4019 | O34: =IF(C34="","",L34-J34) -> 673.30603 | R34: =IF(C34="","",$J$14) -> 0 | S34: =IF(C34="","",$J$15) -> 0 | T34: =IF(C34="","",C34-O34) -> 52188.73 | W34: =IF(C34="","",$W$22) -> 1709.4019
A35: 13 | B35: =IF(C35="","",EDATE($B$22,A35)) -> 44738 | C35: =IF(T34<=0.1,"",T34) -> 52188.73 | F35: =IF(C35="","",(C35*$J$12)) -> 913.30277 | H35: =IF(F35="","",(F35*0.12)) -> 109.59633 | J35: =IF(F35="","",F35+H35) -> 1022.8991 | L35: =IF(H35="","",$J$16) -> 1709.4019 | O35: =IF(C35="","",L35-J35) -> 686.50283 | R35: =IF(C35="","",$J$14) -> 0 | S35: =IF(C35="","",$J$15) -> 0 | T35: =IF(C35="","",C35-O35) -> 51502.227 | W35: =IF(C35="","",$W$22) -> 1709.4019
A36: 14 | B36: =IF(C36="","",EDATE($B$22,A36)) -> 44768 | C36: =IF(T35<=0.1,"",T35) -> 51502.227 | F36: =IF(C36="","",(C36*$J$12)) -> 901.28897 | H36: =IF(F36="","",(F36*0.12)) -> 108.15468 | J36: =IF(F36="","",F36+H36) -> 1009.4436 | L36: =IF(H36="","",$J$16) -> 1709.4019 | O36: =IF(C36="","",L36-J36) -> 699.95828 | R36: =IF(C36="","",$J$14) -> 0 | S36: =IF(C36="","",$J$15) -> 0 | T36: =IF(C36="","",C36-O36) -> 50802.269 | W36: =IF(C36="","",$W$22) -> 1709.4019
A37: 15 | B37: =IF(C37="","",EDATE($B$22,A37)) -> 44799 | C37: =IF(T36<=0.1,"",T36) -> 50802.269 | F37: =IF(C37="","",(C37*$J$12)) -> 889.0397 | H37: =IF(F37="","",(F37*0.12)) -> 106.68476 | J37: =IF(F37="","",F37+H37) -> 995.72446 | L37: =IF(H37="","",$J$16) -> 1709.4019 | O37: =IF(C37="","",L37-J37) -> 713.67747 | R37: =IF(C37="","",$J$14) -> 0 | S37: =IF(C37="","",$J$15) -> 0 | T37: =IF(C37="","",C37-O37) -> 50088.591 | W37: =IF(C37="","",$W$22) -> 1709.4019
A38: 16 | B38: =IF(C38="","",EDATE($B$22,A38)) -> 44830 | C38: =IF(T37<=0.1,"",T37) -> 50088.591 | F38: =IF(C38="","",(C38*$J$12)) -> 876.55034 | H38: =IF(F38="","",(F38*0.12)) -> 105.18604 | J38: =IF(F38="","",F38+H38) -> 981.73639 | L38: =IF(H38="","",$J$16) -> 1709.4019 | O38: =IF(C38="","",L38-J38) -> 727.66554 | R38: =IF(C38="","",$J$14) -> 0 | S38: =IF(C38="","",$J$15) -> 0 | T38: =IF(C38="","",C38-O38) -> 49360.926 | W38: =IF(C38="","",$W$22) -> 1709.4019
A39: 17 | B39: =IF(C39="","",EDATE($B$22,A39)) -> 44860 | C39: =IF(T38<=0.1,"",T38) -> 49360.926 | F39: =IF(C39="","",(C39*$J$12)) -> 863.8162 | H39: =IF(F39="","",(F39*0.12)) -> 103.65794 | J39: =IF(F39="","",F39+H39) -> 967.47414 | L39: =IF(H39="","",$J$16) -> 1709.4019 | O39: =IF(C39="","",L39-J39) -> 741.92779 | R39: =IF(C39="","",$J$14) -> 0 | S39: =IF(C39="","",$J$15) -> 0 | T39: =IF(C39="","",C39-O39) -> 48618.998 | W39: =IF(C39="","",$W$22) -> 1709.4019
A40: 18 | B40: =IF(C40="","",EDATE($B$22,A40)) -> 44891 | C40: =IF(T39<=0.1,"",T39) -> 48618.998 | F40: =IF(C40="","",(C40*$J$12)) -> 850.83246 | H40: =IF(F40="","",(F40*0.12)) -> 102.0999 | J40: =IF(F40="","",F40+H40) -> 952.93236 | L40: =IF(H40="","",$J$16) -> 1709.4019 | O40: =IF(C40="","",L40-J40) -> 756.46957 | R40: =IF(C40="","",$J$14) -> 0 | S40: =IF(C40="","",$J$15) -> 0 | T40: =IF(C40="","",C40-O40) -> 47862.528 | W40: =IF(C40="","",$W$22) -> 1709.4019
... A69: 47 | B69: =IF(C69="","",EDATE($B$22,A69)) -> 45773 | C69: =IF(T68<=0.1,"",T68) -> 19450.176 | F69: =IF(C69="","",(C69*$J$12)) -> 340.37807 | H69: =IF(F69="","",(F69*0.12)) -> 40.845369 | J69: =IF(F69="","",F69+H69) -> 381.22344 | L69: =IF(H69="","",$J$16) -> 1709.4019 | O69: =IF(C69="","",L69-J69) -> 1328.1785 | R69: =IF(C69="","",$J$14) -> 0 | S69: =IF(C69="","",$J$15) -> 0 | T69: =IF(C69="","",C69-O69) -> 18121.997 | W69: =IF(C69="","",$W$22) -> 1709.4019
L70: =IF(H70="","",$J$16) | R70: =IF(C70="","",$J$14) | S70: =IF(C70="","",$J$15) | T70: =IF(C70="","",C70-O70)

Sheet Detalle Cuota especial
C7: Capital | E7: 40000
C8: Tasa de interés | E8: 0.05 | L8: =(E8*1.12) -> 0.056 | AA8: Utilidad Neta Inversor
C9: Plazo (Meses) | E9: 6 | AB9: =SUM(AD18:AD52) -> 45570
C10: Cuota mensual (sin servicios) | E10: =G18+I18+E11+E12 -> 2735
C11: Seguro | E11: 350
C12: GPS | E12: 145
C13: Cuota mensual | E13: =SUM(E10:G12) -> 3230
C14: Inversionista | E14: 0.7
C15: Cash-in | E15: 0.3
AB16: Con impuestos | AD16: Sin impuestos
A17: No. Cuota | B17: Mes | C17: Fecha de pago | D17: Saldo inicial | G17: Intereses | I17: IVA | K17: Interés + IVA | M17: Cuota | P17: Amortización | S17: Seguro | T17: GPS | U17: Saldo final | X17: Cuota mensual | AA17: ISR | AB17: Inversionista | AC17: Cash-In | AD17: Inversionista | AE17: Cash-in
A18: 1 | C18: 43940 | D18: =E7 -> 40000 | G18: =D18*$E$8 -> 2000 | I18: =G18*0.12 -> 240 | K18: =G18+I18 -> 2240 | M18: =G18+I18+$E$11+$E$12 -> 2735 | P18: 0 | S18: =IF(D18="","",$E$11) -> 350 | T18: =IF(D18="","",$E$12) -> 145 | U18: =D18-P18 -> 40000 | X18: =IFERROR(M18+S18+T18,"") -> 3230 | AA18: =G18*0.07 -> 140 | AB18: =(G18+I18)*$E$14 -> 1568 | AC18: =(G18+I18)*$E$15 -> 672 | AD18: =(G18-AA18)*$E$14 -> 1302 | AE18: =(G18-AA18)*$E$15 -> 558
A19: =IF(D19="","",B19+1) -> 2 | B19: 1 | C19: =IF(D19="","",EDATE(C18,B19)) -> 43970 | D19: =IF(U18<=0.1,"",U18) -> 40000 | G19: =IF(D19="","",(D19*$E$8)) -> 2000 | I19: =IF(G19="","",(G19*0.12)) -> 240 | K19: =IF(G19="","",G19+I19) -> 2240 | M19: =IF(I19="","",G19+I19+$E$11+$E$12) -> 2735 | P19: 0 | S19: =IF(D19="","",$E$11) -> 350 | T19: =IF(D19="","",$E$12) -> 145 | U19: =IF(P19="","",D19-P19) -> 40000 | X19: =IF(D19="","",$X$18) -> 3230 | AA19: =IF(G19="","",(G19*0.07)) -> 140 | AB19: =IF(G19="","",(G19+I19)*$E$14) -> 1568 | AC19: =IF(G19="","",(G19+I19)*$E$15) -> 672 | AD19: =IF(G19="","",(G19-AA19)*$E$14) -> 1302 | AE19: =IF(G19="","",(G19-AA19)*$E$15) -> 558
A20: =IF(D20="","",B20+1) -> 3 | B20: 2 | C20: =IF(D20="","",EDATE(C19,B20)) -> 44031 | D20: =IF(U19<=0.1,"",U19) -> 40000 | G20: =IF(D20="","",(D20*$E$8)) -> 2000 | I20: =IF(G20="","",(G20*0.12)) -> 240 | K20: =IF(G20="","",G20+I20) -> 2240 | M20: =IF(I20="","",G20+I20+$E$11+$E$12) -> 2735 | P20: 0 | S20: =IF(D20="","",$E$11) -> 350 | T20: =IF(D20="","",$E$12) -> 145 | U20: =IF(P20="","",D20-P20) -> 40000 | X20: =IF(D20="","",$X$18) -> 3230 | AA20: =IF(G20="","",(G20*0.07)) -> 140 | AB20: =IF(G20="","",(G20+I20)*$E$14) -> 1568 | AC20: =IF(G20="","",(G20+I20)*$E$15) -> 672 | AD20: =IF(G20="","",(G20-AA20)*$E$14) -> 1302 | AE20: =IF(G20="","",(G20-AA20)*$E$15) -> 558
A21: =IF(D21="","",B21+1) -> 4 | B21: 3 | C21: =IF(D21="","",EDATE(C20,B21)) -> 44123 | D21: =IF(U20<=0.1,"",U20) -> 40000 | G21: =IF(D21="","",(D21*$E$8)) -> 2000 | I21: =IF(G21="","",(G21*0.12)) -> 240 | K21: =IF(G21="","",G21+I21) -> 2240 | M21: =IF(I21="","",G21+I21+$E$11+$E$12) -> 2735 | P21: 0 | S21: =IF(D21="","",$E$11) -> 350 | T21: =IF(D21="","",$E$12) -> 145 | U21: =IF(P21="","",D21-P21) -> 40000 | X21: =IF(D21="","",$X$18) -> 3230 | AA21: =IF(G21="","",(G21*0.07)) -> 140 | AB21: =IF(G21="","",(G21+I21)*$E$14) -> 1568 | AC21: =IF(G21="","",(G21+I21)*$E$15) -> 672 | AD21: =IF(G21="","",(G21-AA21)*$E$14) -> 1302 | AE21: =IF(G21="","",(G21-AA21)*$E$15) -> 558
A22: =IF(D22="","",B22+1) -> 5 | B22: 4 | C22: =IF(D22="","",EDATE(C21,B22)) -> 44246 | D22: =IF(U21<=0.1,"",U21) -> 40000 | G22: =IF(D22="","",(D22*$E$8)) -> 2000 | I22: =IF(G22="","",(G22*0.12)) -> 240 | K22: =IF(G22="","",G22+I22) -> 2240 | M22: =IF(I22="","",G22+I22+$E$11+$E$12) -> 2735 | P22: 0 | S22: =IF(P22="","",$E$11) -> 350 | T22: =IF(P22="","",$E$12) -> 145 | U22: =IF(P22="","",D22-P22) -> 40000 | X22: =IF(P22="","",$X$18) -> 3230 | AA22: =IF(G22="","",(G22*0.07)) -> 140 | AB22: =IF(G22="","",(G22+I22)*$E$14) -> 1568 | AC22: =IF(G22="","",(G22+I22)*$E$15) -> 672 | AD22: =IF(G22="","",(G22-AA22)*$E$14) -> 1302 | AE22: =IF(G22="","",(G22-AA22)*$E$15) -> 558
A23: =IF(D23="","",B23+1) -> 6 | B23: 5 | C23: =IF(D23="","",EDATE(C22,B23)) -> 44396 | D23: =IF(U22<=0.1,"",U22) -> 40000 | G23: =IF(D23="","",(D23*$E$8)) -> 2000 | I23: =IF(G23="","",(G23*0.12)) -> 240 | K23: =IF(G23="","",G23+I23) -> 2240 | M23: =IF(I23="","",G23+I23+$E$11+$E$12) -> 2735 | P23: 0 | S23: =IF(P23="","",$E$11) -> 350 | T23: =IF(P23="","",$E$12) -> 145 | U23: =IF(P23="","",D23-P23) -> 40000 | X23: =IF(P23="","",$X$18) -> 3230 | AA23: =IF(G23="","",(G23*0.07)) -> 140 | AB23: =IF(G23="","",(G23+I23)*$E$14) -> 1568 | AC23: =IF(G23="","",(G23+I23)*$E$15) -> 672 | AD23: =IF(G23="","",(G23-AA23)*$E$14) -> 1302 | AE23: =IF(G23="","",(G23-AA23)*$E$15) -> 558
A24: =IF(D24="","",B24+1) -> 7 | B24: 6 | C24: =IF(D24="","",EDATE(C23,B24)) -> 44580 | D24: =IF(U23<=0.1,"",U23) -> 40000 | G24: =IF(D24="","",(D24*$E$8)) -> 2000 | I24: =IF(G24="","",(G24*0.12)) -> 240 | K24: =IF(G24="","",G24+I24) -> 2240 | M24: =IF(I24="","",G24+I24+$E$11+$E$12) -> 2735 | P24: 0 | S24: =IF(P24="","",$E$11) -> 350 | T24: =IF(P24="","",$E$12) -> 145 | U24: =IF(P24="","",D24-P24) -> 40000 | X24: =IF(P24="","",$X$18) -> 3230 | AA24: =IF(G24="","",(G24*0.07)) -> 140 | AB24: =IF(G24="","",(G24+I24)*$E$14) -> 1568 | AC24: =IF(G24="","",(G24+I24)*$E$15) -> 672 | AD24: =IF(G24="","",(G24-AA24)*$E$14) -> 1302 | AE24: =IF(G24="","",(G24-AA24)*$E$15) -> 558
A25: =IF(D25="","",B25+1) -> 8 | B25: 7 | C25: =IF(D25="","",EDATE(C24,B25)) -> 44792 | D25: =IF(U24<=0.1,"",U24) -> 40000 | G25: =IF(D25="","",(D25*$E$8)) -> 2000 | I25: =IF(G25="","",(G25*0.12)) -> 240 | K25: =IF(G25="","",G25+I25) -> 2240 | M25: =IF(I25="","",G25+I25+$E$11+$E$12) -> 2735 | P25: 0 | S25: =IF(P25="","",$E$11) -> 350 | T25: =IF(P25="","",$E$12) -> 145 | U25: =IF(P25="","",D25-P25) -> 40000 | X25: =IF(P25="","",$X$18) -> 3230 | AA25: =IF(G25="","",(G25*0.07)) -> 140 | AB25: =IF(G25="","",(G25+I25)*$E$14) -> 1568 | AC25: =IF(G25="","",(G25+I25)*$E$15) -> 672 | AD25: =IF(G25="","",(G25-AA25)*$E$14) -> 1302 | AE25: =IF(G25="","",(G25-AA25)*$E$15) -> 558
A26: =IF(D26="","",B26+1) -> 9 | B26: 8 | C26: =IF(D26="","",EDATE(C25,B26)) -> 45035 | D26: =IF(U25<=0.1,"",U25) -> 40000 | G26: =IF(D26="","",(D26*$E$8)) -> 2000 | I26: =IF(G26="","",(G26*0.12)) -> 240 | K26: =IF(G26="","",G26+I26) -> 2240 | M26: =IF(I26="","",G26+I26+$E$11+$E$12) -> 2735 | P26: 0 | S26: =IF(P26="","",$E$11) -> 350 | T26: =IF(P26="","",$E$12) -> 145 | U26: =IF(P26="","",D26-P26) -> 40000 | X26: =IF(P26="","",$X$18) -> 3230 | AA26: =IF(G26="","",(G26*0.07)) -> 140 | AB26: =IF(G26="","",(G26+I26)*$E$14) -> 1568 | AC26: =IF(G26="","",(G26+I26)*$E$15) -> 672 | AD26: =IF(G26="","",(G26-AA26)*$E$14) -> 1302 | AE26: =IF(G26="","",(G26-AA26)*$E$15) -> 558
A27: =IF(D27="","",B27+1) -> 10 | B27: 9 | C27: =IF(D27="","",EDATE(C26,B27)) -> 45310 | D27: =IF(U26<=0.1,"",U26) -> 40000 | G27: =IF(D27="","",(D27*$E$8)) -> 2000 | I27: =IF(G27="","",(G27*0.12)) -> 240 | K27: =IF(G27="","",G27+I27) -> 2240 | M27: =IF(I27="","",G27+I27+$E$11+$E$12) -> 2735 | P27: 0 | S27: =IF(P27="","",$E$11) -> 350 | T27: =IF(P27="","",$E$12) -> 145 | U27: =IF(P27="","",D27-P27) -> 40000 | X27: =IF(P27="","",$X$18) -> 3230 | AA27: =IF(G27="","",(G27*0.07)) -> 140 | AB27: =IF(G27="","",(G27+I27)*$E$14) -> 1568 | AC27: =IF(G27="","",(G27+I27)*$E$15) -> 672 | AD27: =IF(G27="","",(G27-AA27)*$E$14) -> 1302 | AE27: =IF(G27="","",(G27-AA27)*$E$15) -> 558
A28: =IF(D28="","",B28+1) -> 11 | B28: 10 | C28: =IF(D28="","",EDATE(C27,B28)) -> 45615 | D28: =IF(U27<=0.1,"",U27) -> 40000 | G28: =IF(D28="","",(D28*$E$8)) -> 2000 | I28: =IF(G28="","",(G28*0.12)) -> 240 | K28: =IF(G28="","",G28+I28) -> 2240 | M28: =IF(I28="","",G28+I28+$E$11+$E$12) -> 2735 | P28: 0 | S28: =IF(P28="","",$E$11) -> 350 | T28: =IF(P28="","",$E$12) -> 145 | U28: =IF(P28="","",D28-P28) -> 40000 | X28: =IF(P28="","",$X$18) -> 3230 | AA28: =IF(G28="","",(G28*0.07)) -> 140 | AB28: =IF(G28="","",(G28+I28)*$E$14) -> 1568 | AC28: =IF(G28="","",(G28+I28)*$E$15) -> 672 | AD28: =IF(G28="","",(G28-AA28)*$E$14) -> 1302 | AE28: =IF(G28="","",(G28-AA28)*$E$15) -> 558
A29: =IF(D29="","",B29+1) -> 12 | B29: 11 | C29: =IF(D29="","",EDATE(C28,B29)) -> 45949 | D29: =IF(U28<=0.1,"",U28) -> 40000 | G29: =IF(D29="","",(D29*$E$8)) -> 2000 | I29: =IF(G29="","",(G29*0.12)) -> 240 | K29: =IF(G29="","",G29+I29) -> 2240 | M29: =IF(I29="","",G29+I29+$E$11+$E$12) -> 2735 | P29: 0 | S29: =IF(P29="","",$E$11) -> 350 | T29: =IF(P29="","",$E$12) -> 145 | U29: =IF(P29="","",D29-P29) -> 40000 | X29: =IF(P29="","",$X$18) -> 3230 | AA29: =IF(G29="","",(G29*0.07)) -> 140 | AB29: =IF(G29="","",(G29+I29)*$E$14) -> 1568 | AC29: =IF(G29="","",(G29+I29)*$E$15) -> 672 | AD29: =IF(G29="","",(G29-AA29)*$E$14) -> 1302 | AE29: =IF(G29="","",(G29-AA29)*$E$15) -> 558
A30: =IF(D30="","",B30+1) -> 13 | B30: 12 | C30: =IF(D30="","",EDATE(C29,B30)) -> 46314 | D30: =IF(U29<=0.1,"",U29) -> 40000 | G30: =IF(D30="","",(D30*$E$8)) -> 2000 | I30: =IF(G30="","",(G30*0.12)) -> 240 | K30: =IF(G30="","",G30+I30) -> 2240 | M30: =IF(I30="","",G30+I30+$E$11+$E$12) -> 2735 | P30: 0 | S30: =IF(P30="","",$E$11) -> 350 | T30: =IF(P30="","",$E$12) -> 145 | U30: =IF(P30="","",D30-P30) -> 40000 | X30: =IF(P30="","",$X$18) -> 3230 | AA30: =IF(G30="","",(G30*0.07)) -> 140 | AB30: =IF(G30="","",(G30+I30)*$E$14) -> 1568 | AC30: =IF(G30="","",(G30+I30)*$E$15) -> 672 | AD30: =IF(G30="","",(G30-AA30)*$E$14) -> 1302 | AE30: =IF(G30="","",(G30-AA30)*$E$15) -> 558
A31: =IF(D31="","",B31+1) -> 14 | B31: 13 | C31: =IF(D31="","",EDATE(C30,B31)) -> 46710 | D31: =IF(U30<=0.1,"",U30) -> 40000 | G31: =IF(D31="","",(D31*$E$8)) -> 2000 | I31: =IF(G31="","",(G31*0.12)) -> 240 | K31: =IF(G31="","",G31+I31) -> 2240 | M31: =IF(I31="","",G31+I31+$E$11+$E$12) -> 2735 | P31: 0 | S31: =IF(P31="","",$E$11) -> 350 | T31: =IF(P31="","",$E$12) -> 145 | U31: =IF(P31="","",D31-P31) -> 40000 | X31: =IF(P31="","",$X$18) -> 3230 | AA31: =IF(G31="","",(G31*0.07)) -> 140 | AB31: =IF(G31="","",(G31+I31)*$E$14) -> 1568 | AC31: =IF(G31="","",(G31+I31)*$E$15) -> 672 | AD31: =IF(G31="","",(G31-AA31)*$E$14) -> 1302 | AE31: =IF(G31="","",(G31-AA31)*$E$15) -> 558
A32: =IF(D32="","",B32+1) -> 15 | B32: 14 | C32: =IF(D32="","",EDATE(C31,B32)) -> 47137 | D32: =IF(U31<=0.1,"",U31) -> 40000 | G32: =IF(D32="","",(D32*$E$8)) -> 2000 | I32: =IF(G32="","",(G32*0.12)) -> 240 | K32: =IF(G32="","",G32+I32) -> 2240 | M32: =IF(I32="","",G32+I32+$E$11+$E$12) -> 2735 | P32: 0 | S32: =IF(P32="","",$E$11) -> 350 | T32: =IF(P32="","",$E$12) -> 145 | U32: =IF(P32="","",D32-P32) -> 40000 | X32: =IF(P32="","",$X$18) -> 3230 | AA32: =IF(G32="","",(G32*0.07)) -> 140 | AB32: =IF(G32="","",(G32+I32)*$E$14) -> 1568 | AC32: =IF(G32="","",(G32+I32)*$E$15) -> 672 | AD32: =IF(G32="","",(G32-AA32)*$E$14) -> 1302 | AE32: =IF(G32="","",(G32-AA32)*$E$15) -> 558
A33: =IF(D33="","",B33+1) -> 16 | B33: 15 | C33: =IF(D33="","",EDATE(C32,B33)) -> 47592 | D33: =IF(U32<=0.1,"",U32) -> 40000 | G33: =IF(D33="","",(D33*$E$8)) -> 2000 | I33: =IF(G33="","",(G33*0.12)) -> 240 | K33: =IF(G33="","",G33+I33) -> 2240 | M33: =IF(I33="","",G33+I33+$E$11+$E$12) -> 2735 | P33: 0 | S33: =IF(P33="","",$E$11) -> 350 | T33: =IF(P33="","",$E$12) -> 145 | U33: =IF(P33="","",D33-P33) -> 40000 | X33: =IF(P33="","",$X$18) -> 3230 | AA33: =IF(G33="","",(G33*0.07)) -> 140 | AB33: =IF(G33="","",(G33+I33)*$E$14) -> 1568 | AC33: =IF(G33="","",(G33+I33)*$E$15) -> 672 | AD33: =IF(G33="","",(G33-AA33)*$E$14) -> 1302 | AE33: =IF(G33="","",(G33-AA33)*$E$15) -> 558
A34: =IF(D34="","",B34+1) -> 17 | B34: 16 | C34: =IF(D34="","",EDATE(C33,B34)) -> 48079 | D34: =IF(U33<=0.1,"",U33) -> 40000 | G34: =IF(D34="","",(D34*$E$8)) -> 2000 | I34: =IF(G34="","",(G34*0.12)) -> 240 | K34: =IF(G34="","",G34+I34) -> 2240 | M34: =IF(I34="","",G34+I34+$E$11+$E$12) -> 2735 | P34: 0 | S34: =IF(P34="","",$E$11) -> 350 | T34: =IF(P34="","",$E$12) -> 145 | U34: =IF(P34="","",D34-P34) -> 40000 | X34: =IF(P34="","",$X$18) -> 3230 | AA34: =IF(G34="","",(G34*0.07)) -> 140 | AB34: =IF(G34="","",(G34+I34)*$E$14) -> 1568 | AC34: =IF(G34="","",(G34+I34)*$E$15) -> 672 | AD34: =IF(G34="","",(G34-AA34)*$E$14) -> 1302 | AE34: =IF(G34="","",(G34-AA34)*$E$15) -> 558
A35: =IF(D35="","",B35+1) -> 18 | B35: 17 | C35: =IF(D35="","",EDATE(C34,B35)) -> 48598 | D35: =IF(U34<=0.1,"",U34) -> 40000 | G35: =IF(D35="","",(D35*$E$8)) -> 2000 | I35: =IF(G35="","",(G35*0.12)) -> 240 | K35: =IF(G35="","",G35+I35) -> 2240 | M35: =IF(I35="","",G35+I35+$E$11+$E$12) -> 2735 | P35: 0 | S35: =IF(D35="","",$E$11) -> 350 | T35: =IF(P35="","",$E$12) -> 145 | U35: =IF(P35="","",D35-P35) -> 40000 | X35: =IF(P35="","",$X$18) -> 3230 | AA35: =IF(G35="","",(G35*0.07)) -> 140 | AB35: =IF(G35="","",(G35+I35)*$E$14) -> 1568 | AC35: =IF(G35="","",(G35+I35)*$E$15) -> 672 | AD35: =IF(G35="","",(G35-AA35)*$E$14) -> 1302 | AE35: =IF(G35="","",(G35-AA35)*$E$15) -> 558
A36: =IF(D36="","",B36+1) -> 19 | B36: 18 | C36: =IF(D36="","",EDATE(C35,B36)) -> 49144 | D36: =IF(U35<=0.1,"",U35) -> 40000 | G36: =IF(D36="","",(D36*$E$8)) -> 2000 | I36: =IF(G36="","",(G36*0.12)) -> 240 | K36: =IF(G36="","",G36+I36) -> 2240 | M36: =IF(I36="","",G36+I36+$E$11+$E$12) -> 2735 | P36: 0 | S36: =IF(D36="","",$E$11) -> 350 | T36: =IF(D36="","",$E$12) -> 145 | U36: =IF(P36="","",D36-P36) -> 40000 | X36: =IF(D36="","",$X$18) -> 3230 | AA36: =IF(G36="","",(G36*0.07)) -> 140 | AB36: =IF(G36="","",(G36+I36)*$E$14) -> 1568 | AC36: =IF(G36="","",(G36+I36)*$E$15) -> 672 | AD36: =IF(G36="","",(G36-AA36)*$E$14) -> 1302 | AE36: =IF(G36="","",(G36-AA36)*$E$15) -> 558
A37: =IF(D37="","",B37+1) -> 20 | B37: 19 | C37: =IF(D37="","",EDATE(C36,B37)) -> 49724 | D37: =IF(U36<=0.1,"",U36) -> 40000 | G37: =IF(D37="","",(D37*$E$8)) -> 2000 | I37: =IF(G37="","",(G37*0.12)) -> 240 | K37: =IF(G37="","",G37+I37) -> 2240 | M37: =IF(I37="","",G37+I37+$E$11+$E$12) -> 2735 | P37: 0 | S37: =IF(D37="","",$E$11) -> 350 | T37: =IF(D37="","",$E$12) -> 145 | U37: =IF(P37="","",D37-P37) -> 40000 | X37: =IF(D37="","",$X$18) -> 3230 | AA37: =IF(G37="","",(G37*0.07)) -> 140 | AB37: =IF(G37="","",(G37+I37)*$E$14) -> 1568 | AC37: =IF(G37="","",(G37+I37)*$E$15) -> 672 | AD37: =IF(G37="","",(G37-AA37)*$E$14) -> 1302 | AE37: =IF(G37="","",(G37-AA37)*$E$15) -> 558
A38: =IF(D38="","",B38+1) -> 21 | B38: 20 | C38: =IF(D38="","",EDATE(C37,B38)) -> 50332 | D38: =IF(U37<=0.1,"",U37) -> 40000 | G38: =IF(D38="","",(D38*$E$8)) -> 2000 | I38: =IF(G38="","",(G38*0.12)) -> 240 | K38: =IF(G38="","",G38+I38) -> 2240 | M38: =IF(I38="","",G38+I38+$E$11+$E$12) -> 2735 | P38: 0 | S38: =IF(D38="","",$E$11) -> 350 | T38: =IF(D38="","",$E$12) -> 145 | U38: =IF(P38="","",D38-P38) -> 40000 | X38: =IF(D38="","",$X$18) -> 3230 | AA38: =IF(G38="","",(G38*0.07)) -> 140 | AB38: =IF(G38="","",(G38+I38)*$E$14) -> 1568 | AC38: =IF(G38="","",(G38+I38)*$E$15) -> 672 | AD38: =IF(G38="","",(G38-AA38)*$E$14) -> 1302 | AE38: =IF(G38="","",(G38-AA38)*$E$15) -> 558
A39: =IF(D39="","",B39+1) -> 22 | B39: 21 | C39: =IF(D39="","",EDATE(C38,B39)) -> 50970 | D39: =IF(U38<=0.1,"",U38) -> 40000 | G39: =IF(D39="","",(D39*$E$8)) -> 2000 | I39: =IF(G39="","",(G39*0.12)) -> 240 | K39: =IF(G39="","",G39+I39) -> 2240 | M39: =IF(I39="","",G39+I39+$E$11+$E$12) -> 2735 | P39: 0 | S39: =IF(D39="","",$E$11) -> 350 | T39: =IF(D39="","",$E$12) -> 145 | U39: =IF(P39="","",D39-P39) -> 40000 | X39: =IF(D39="","",$X$18) -> 3230 | AA39: =IF(G39="","",(G39*0.07)) -> 140 | AB39: =IF(G39="","",(G39+I39)*$E$14) -> 1568 | AC39: =IF(G39="","",(G39+I39)*$E$15) -> 672 | AD39: =IF(G39="","",(G39-AA39)*$E$14) -> 1302 | AE39: =IF(G39="","",(G39-AA39)*$E$15) -> 558
A40: =IF(D40="","",B40+1) -> 23 | B40: 22 | C40: =IF(D40="","",EDATE(C39,B40)) -> 51640 | D40: =IF(U39<=0.1,"",U39) -> 40000 | G40: =IF(D40="","",(D40*$E$8)) -> 2000 | I40: =IF(G40="","",(G40*0.12)) -> 240 | K40: =IF(G40="","",G40+I40) -> 2240 | M40: =IF(I40="","",G40+I40+$E$11+$E$12) -> 2735 | P40: 0 | S40: =IF(D40="","",$E$11) -> 350 | T40: =IF(D40="","",$E$12) -> 145 | U40: =IF(P40="","",D40-P40) -> 40000 | X40: =IF(D40="","",$X$18) -> 3230 | AA40: =IF(G40="","",(G40*0.07)) -> 140 | AB40: =IF(G40="","",(G40+I40)*$E$14) -> 1568 | AC40: =IF(G40="","",(G40+I40)*$E$15) -> 672 | AD40: =IF(G40="","",(G40-AA40)*$E$14) -> 1302 | AE40: =IF(G40="","",(G40-AA40)*$E$15) -> 558
A41: =IF(D41="","",B41+1) -> 24 | B41: 23 | C41: =IF(D41="","",EDATE(C40,B41)) -> 52340 | D41: =IF(U40<=0.1,"",U40) -> 40000 | G41: =IF(D41="","",(D41*$E$8)) -> 2000 | I41: =IF(G41="","",(G41*0.12)) -> 240 | K41: =IF(G41="","",G41+I41) -> 2240 | M41: =IF(I41="","",G41+I41+$E$11+$E$12) -> 2735 | P41: 0 | S41: =IF(D41="","",$E$11) -> 350 | T41: =IF(D41="","",$E$12) -> 145 | U41: =IF(P41="","",D41-P41) -> 40000 | X41: =IF(D41="","",$X$18) -> 3230 | AA41: =IF(G41="","",(G41*0.07)) -> 140 | AB41: =IF(G41="","",(G41+I41)*$E$14) -> 1568 | AC41: =IF(G41="","",(G41+I41)*$E$15) -> 672 | AD41: =IF(G41="","",(G41-AA41)*$E$14) -> 1302 | AE41: =IF(G41="","",(G41-AA41)*$E$15) -> 558
A42: =IF(D42="","",B42+1) -> 25 | B42: 24 | C42: =IF(D42="","",EDATE(C41,B42)) -> 53071 | D42: =IF(U41<=0.1,"",U41) -> 40000 | G42: =IF(D42="","",(D42*$E$8)) -> 2000 | I42: =IF(G42="","",(G42*0.12)) -> 240 | K42: =IF(G42="","",G42+I42) -> 2240 | M42: =IF(I42="","",G42+I42+$E$11+$E$12) -> 2735 | P42: 0 | S42: =IF(D42="","",$E$11) -> 350 | T42: =IF(D42="","",$E$12) -> 145 | U42: =IF(P42="","",D42-P42) -> 40000 | X42: =IF(D42="","",$X$18) -> 3230 | AA42: =IF(G42="","",(G42*0.07)) -> 140 | AB42: =IF(G42="","",(G42+I42)*$E$14) -> 1568 | AC42: =IF(G42="","",(G42+I42)*$E$15) -> 672 | AD42: =IF(G42="","",(G42-AA42)*$E$14) -> 1302 | AE42: =IF(G42="","",(G42-AA42)*$E$15) -> 558
A43: =IF(D43="","",B43+1) -> 26 | B43: 25 | C43: =IF(D43="","",EDATE(C42,B43)) -> 53831 | D43: =IF(U42<=0.1,"",U42) -> 40000 | G43: =IF(D43="","",(D43*$E$8)) -> 2000 | I43: =IF(G43="","",(G43*0.12)) -> 240 | K43: =IF(G43="","",G43+I43) -> 2240 | M43: =IF(I43="","",G43+I43+$E$11+$E$12) -> 2735 | P43: 0 | S43: =IF(D43="","",$E$11) -> 350 | T43: =IF(D43="","",$E$12) -> 145 | U43: =IF(P43="","",D43-P43) -> 40000 | X43: =IF(D43="","",$X$18) -> 3230 | AA43: =IF(G43="","",(G43*0.07)) -> 140 | AB43: =IF(G43="","",(G43+I43)*$E$14) -> 1568 | AC43: =IF(G43="","",(G43+I43)*$E$15) -> 672 | AD43: =IF(G43="","",(G43-AA43)*$E$14) -> 1302 | AE43: =IF(G43="","",(G43-AA43)*$E$15) -> 558
A44: =IF(D44="","",B44+1) -> 27 | B44: 26 | C44: =IF(D44="","",EDATE(C43,B44)) -> 54623 | D44: =IF(U43<=0.1,"",U43) -> 40000 | G44: =IF(D44="","",(D44*$E$8)) -> 2000 | I44: =IF(G44="","",(G44*0.12)) -> 240 | K44: =IF(G44="","",G44+I44) -> 2240 | M44: =IF(I44="","",G44+I44+$E$11+$E$12) -> 2735 | P44: 0 | S44: =IF(D44="","",$E$11) -> 350 | T44: =IF(D44="","",$E$12) -> 145 | U44: =IF(P44="","",D44-P44) -> 40000 | X44: =IF(D44="","",$X$18) -> 3230 | AA44: =IF(G44="","",(G44*0.07)) -> 140 | AB44: =IF(G44="","",(G44+I44)*$E$14) -> 1568 | AC44: =IF(G44="","",(G44+I44)*$E$15) -> 672 | AD44: =IF(G44="","",(G44-AA44)*$E$14) -> 1302 | AE44: =IF(G44="","",(G44-AA44)*$E$15) -> 558
A45: =IF(D45="","",B45+1) -> 28 | B45: 27 | C45: =IF(D45="","",EDATE(C44,B45)) -> 55445 | D45: =IF(U44<=0.1,"",U44) -> 40000 | G45: =IF(D45="","",(D45*$E$8)) -> 2000 | I45: =IF(G45="","",(G45*0.12)) -> 240 | K45: =IF(G45="","",G45+I45) -> 2240 | M45: =IF(I45="","",G45+I45+$E$11+$E$12) -> 2735 | P45: 0 | S45: =IF(D45="","",$E$11) -> 350 | T45: =IF(D45="","",$E$12) -> 145 | U45: =IF(P45="","",D45-P45) -> 40000 | X45: =IF(D45="","",$X$18) -> 3230 | AA45: =IF(G45="","",(G45*0.07)) -> 140 | AB45: =IF(G45="","",(G45+I45)*$E$14) -> 1568 | AC45: =IF(G45="","",(G45+I45)*$E$15) -> 672 | AD45: =IF(G45="","",(G45-AA45)*$E$14) -> 1302 | AE45: =IF(G45="","",(G45-AA45)*$E$15) -> 558
A46: =IF(D46="","",B46+1) -> 29 | B46: 28 | C46: =IF(D46="","",EDATE(C45,B46)) -> 56299 | D46: =IF(U45<=0.1,"",U45) -> 40000 | G46: =IF(D46="","",(D46*$E$8)) -> 2000 | I46: =IF(G46="","",(G46*0.12)) -> 240 | K46: =IF(G46="","",G46+I46) -> 2240 | M46: =IF(I46="","",G46+I46+$E$11+$E$12) -> 2735 | P46: 0 | S46: =IF(D46="","",$E$11) -> 350 | T46: =IF(D46="","",$E$12) -> 145 | U46: =IF(P46="","",D46-P46) -> 40000 | X46: =IF(D46="","",$X$18) -> 3230 | AA46: =IF(G46="","",(G46*0.07)) -> 140 | AB46: =IF(G46="","",(G46+I46)*$E$14) -> 1568 | AC46: =IF(G46="","",(G46+I46)*$E$15) -> 672 | AD46: =IF(G46="","",(G46-AA46)*$E$14) -> 1302 | AE46: =IF(G46="","",(G46-AA46)*$E$15) -> 558
A47: =IF(D47="","",B47+1) -> 30 | B47: 29 | C47: =IF(D47="","",EDATE(C46,B47)) -> 57180 | D47: =IF(U46<=0.1,"",U46) -> 40000 | G47: =IF(D47="","",(D47*$E$8)) -> 2000 | I47: =IF(G47="","",(G47*0.12)) -> 240 | K47: =IF(G47="","",G47+I47) -> 2240 | M47: =IF(I47="","",G47+I47+$E$11+$E$12) -> 2735 | P47: 0 | S47: =IF(D47="","",$E$11) -> 350 | T47: =IF(D47="","",$E$12) -> 145 | U47: =IF(P47="","",D47-P47) -> 40000 | X47: =IF(D47="","",$X$18) -> 3230 | AA47: =IF(G47="","",(G47*0.07)) -> 140 | AB47: =IF(G47="","",(G47+I47)*$E$14) -> 1568 | AC47: =IF(G47="","",(G47+I47)*$E$15) -> 672 | AD47: =IF(G47="","",(G47-AA47)*$E$14) -> 1302 | AE47: =IF(G47="","",(G47-AA47)*$E$15) -> 558
... A51: =IF(D51="","",B51+1) -> 34 | B51: 33 | C51: =IF(D51="","",EDATE(C50,B51)) -> 61016 | D51: =IF(U50<=0.1,"",U50) -> 40000 | G51: =IF(D51="","",(D51*$E$8)) -> 2000 | I51: =IF(G51="","",(G51*0.12)) -> 240 | K51: =IF(G51="","",G51+I51) -> 2240 | M51: =IF(I51="","",G51+I51+$E$11+$E$12) -> 2735 | P51: 0 | S51: =IF(D51="","",$E$11) -> 350 | T51: =IF(D51="","",$E$12) -> 145 | U51: =IF(P51="","",D51-P51) -> 40000 | X51: =IF(D51="","",$X$18) -> 3230 | AA51: =IF(G51="","",(G51*0.07)) -> 140 | AB51: =IF(G51="","",(G51+I51)*$E$14) -> 1568 | AC51: =IF(G51="","",(G51+I51)*$E$15) -> 672 | AD51: =IF(G51="","",(G51-AA51)*$E$14) -> 1302 | AE51: =IF(G51="","",(G51-AA51)*$E$15) -> 558
A52: =IF(D52="","",B52+1) -> 35 | B52: 34 | C52: =IF(D52="","",EDATE(C51,B52)) -> 62051 | D52: =IF(U51<=0.1,"",U51) -> 40000 | G52: =IF(D52="","",(D52*$E$8)) -> 2000 | I52: =IF(G52="","",(G52*0.12)) -> 240 | K52: =IF(G52="","",G52+I52) -> 2240 | M52: =IF(I52="","",G52+I52+$E$11+$E$12) -> 2735 | S52: =IF(D52="","",$E$11) -> 350 | T52: =IF(D52="","",$E$12) -> 145 | U52: =IF(P52="","",D52-P52) | X52: =IF(D52="","",$X$18) -> 3230 | AA52: =IF(G52="","",(G52*0.07)) -> 140 | AB52: =IF(G52="","",(G52+I52)*$E$14) -> 1568 | AC52: =IF(G52="","",(G52+I52)*$E$15) -> 672 | AD52: =IF(G52="","",(G52-AA52)*$E$14) -> 1302 | AE52: =IF(G52="","",(G52-AA52)*$E$15) -> 558
A53: =IF(D53="","",B53+1) | B53: 35 | C53: =IF(D53="","",EDATE(C52,B53)) | D53: =IF(U52<=0.1,"",U52) | G53: =IF(D53="","",(D53*$E$8)) | I53: =IF(G53="","",(G53*0.12)) | K53: =IF(G53="","",G53+I53) | M53: =IF(I53="","",G53+I53+$E$11+$E$12) | S53: =IF(D53="","",$E$11) | T53: =IF(D53="","",$E$12) | U53: =IF(P53="","",D53-P53) | X53: =IF(D53="","",$X$18) | AA53: =IF(G53="","",(G53*0.07)) | AB53: =IF(G53="","",(G53+I53)*$E$14) | AC53: =IF(G53="","",(G53+I53)*$E$15) | AD53: =IF(G53="","",(G53-AA53)*$E$14) | AE53: =IF(G53="","",(G53-AA53)*$E$15)

Sheet Analisis de pago
B2: Tipo de credito | C2: =FORMULARIO!D61 -> Vehículo
B4: Edad | C4: =FORMULARIO!K9 -> 0 | D4: =IFERROR(VLOOKUP(C4,'Datos - analisis de pago'!B4:C7,2,FALSE),"0") -> 0 | E4: 1 | F4: 2
B5: Residencia | C5: =FORMULARIO!J15 -> 0 | D5: =IFERROR(VLOOKUP(C5,'Datos - analisis de pago'!E4:F20,2,FALSE),0) -> 0 | E5: 1 | F5: 2
B6: Coinciden direcciones? | C6: =FORMULARIO!K21 -> 0 | D6: =IFERROR(VLOOKUP(C6,'Datos - analisis de pago'!H5:I6,2,FALSE),0) -> 0 | E6: 1 | F6: 4 | G6: =SUM(F4:F6) -> 8 | I6: =IF(C2="Hipotecario",IF(D30=0,"",IF(D30<=30,"A",IF(D30<=50,"B",IF(D30<=70,"C",IF(D30<=340,"D",""))))),IF(D30=0,"",IF(D30<=30,"A",IF(D30<=50,"B",IF(D30<=70,"C",IF(D30<=340,"D",""))))))
B7: Estado civil | C7: =FORMULARIO!C13 -> 0 | D7: =IFERROR(VLOOKUP(C7,'Datos - analisis de pago'!B24:C26,2,FALSE),0) -> 0 | E7: 1 | F7: 4
B8: Tiene dependientes | C8: =FORMULARIO!F36 -> 0 | D8: =IFERROR(VLOOKUP(C8,'Datos - analisis de pago'!E24:F25,2,FALSE),0) -> 0 | E8: 1 | F8: 4
B9: Capacidad de endeudamiento | C9: =FORMULARIO!G32 -> 0 | D9: =IFERROR(VLOOKUP(C9,'Datos - analisis de pago'!H24:I30,2,FALSE),0) -> 0 | E9: 2 | F9: 4 | I9: =IF(I6="","","Tasa a Ofrecer")
B10: Dentro de sus egresos paga alguna deuda? | C10: =FORMULARIO!F34 -> 0 | D10: =IFERROR(VLOOKUP(C10,'Datos - analisis de pago'!O24:P25,2,FALSE),0) -> 0 | E10: 1 | F10: 4 | I10: =IF(I6="A","1% - 1.5%",IF(I6="B","1.6% - 2%",IF(I6="C","2.1% - 2.5%",IF(I6="D","3%",""))))
B11: Esta orgulloso de sus actividades? | C11: =FORMULARIO!I38 -> 0 | D11: =IFERROR(VLOOKUP(C11,'Datos - analisis de pago'!L24:M25,2,FALSE),0) -> 0 | E11: 1 | F11: 4 | G11: =SUM(F7:F11) -> 20
B12: Tiene cuenta bancaria | C12: =FORMULARIO!E43 -> 0 | D12: =IFERROR(VLOOKUP(C12,'Datos - analisis de pago'!B33:C34,2,FALSE),0) -> 0 | E12: 1 | F12: 3
B13: Tiene tarjeta de credito | C13: =FORMULARIO!F45 -> 0 | D13: =IFERROR(VLOOKUP(C13,'Datos - analisis de pago'!E33:F34,2,FALSE),0) -> 0 | E13: 0.5 | F13: 3
B14: La tiene al día? | C14: =FORMULARIO!I45 -> 0 | D14: =IFERROR(VLOOKUP(C14,'Datos - analisis de pago'!H33:I34,2,FALSE),0) -> 0 | E14: 0.5 | F14: 7
B15: Cuantos créditos activos tiene? | C15: =FORMULARIO!E49 -> 0 | D15: =IFERROR(VLOOKUP(C15,'Datos - analisis de pago'!N33:O38,2,FALSE),0) -> 0 | E15: 0 | F15: 2
B16: Capacidad de endeudamiento | C16: =FORMULARIO!K51 | D16: =IF(C16<0,10,IFERROR(VLOOKUP(C16,'Datos - analisis de pago'!A51:C150,3,TRUE),0)) -> 0 | E16: 0.5 | F16: 1
B17: Posee cuotas atrasadas? | C17: =FORMULARIO!D53 -> 0 | D17: =IFERROR(VLOOKUP(C17,'Datos - analisis de pago'!R33:S34,2,FALSE),0) -> 0 | E17: 0.5 | F17: 5
B18: Cantidad de cuotas atrasadas | C18: =FORMULARIO!I53 -> 0 | D18: =IFERROR(VLOOKUP(C18,'Datos - analisis de pago'!V33:W38,2,FALSE),0) -> 0 | E18: 0.5 | F18: 7
B19: Es honrado? | C19: =FORMULARIO!C57 -> 0 | D19: =IFERROR(VLOOKUP(C19,'Datos - analisis de pago'!K33:L34,2,FALSE),0) -> 0 | E19: 0.5 | F19: 7 | G19: =SUM(F12:F19) -> 35
B20: Tiene alguna deuda sobre la propiedad | C20: =FORMULARIO!L92 -> 0 | D20: =IFERROR(VLOOKUP(C20,'Datos - analisis de pago'!E40:F41,2,FALSE),0) -> 0 | E20: 0.5 | F20: 5
B21: Tiene IUSI al día? | C21: =FORMULARIO!C98 -> 0 | D21: =IFERROR(VLOOKUP(C21,'Datos - analisis de pago'!E45:F46,2,FALSE),0) -> 0 | E21: 1 | F21: 5
B22: Cuantos trimestres adeuda? | C22: =FORMULARIO!I98 -> 0 | D22: =IFERROR(VLOOKUP(C22,'Datos - analisis de pago'!H45:I48,2,FALSE),0) -> 0 | E22: 0.5 | F22: 5
B23: Que logro tener algo propio! | C23: =FORMULARIO!E100 -> 0 | D23: =IFERROR(VLOOKUP(C23,'Datos - analisis de pago'!H40:I41,2,FALSE),0) -> 0 | E23: 0.5 | F23: 5 | G23: =SUM(F20:F23) -> 20
B24: Cuota nivelada vs. Capacidad de endeudamiento | C24: =FORMULARIO!F67 | D24: =IF(C24="",0,IF(C24>1,10,(IFERROR(VLOOKUP(C24,'Datos - analisis de pago'!A51:B150,2,TRUE),IF(C24<0,10,(IFERROR(VLOOKUP(C24,'Datos - analisis de pago'!A51:B150,2,TRUE),0))))))) -> 0 | E24: 1 | F24: 2.5
B25: Garantia propia | C25: =FORMULARIO!D73 -> 0 | D25: =IFERROR(VLOOKUP(C25,'Datos - analisis de pago'!F51:G52,2,FALSE),0) -> 0 | E25: 1 | F25: 2.5 | G25: =SUM(F24:F25) -> 5
B26: Impuesto de circulacion del año en curso pagado? | C26: =FORMULARIO!H119 -> 0 | D26: =IFERROR(VLOOKUP(C26,'Datos - analisis de pago'!K45:L46,2,FALSE),0) -> 0 | E26: 0.5 | F26: 5
B27: Días en mora? | C27: =FORMULARIO!K119 -> 0 | D27: =IFERROR(VLOOKUP(C27,'Datos - analisis de pago'!P45:Q47,2,FALSE),0) -> 0 | E27: 0.5 | F27: 5
B28: Que logro tener algo propio! | C28: =FORMULARIO!E121 -> 0 | D28: =IFERROR(VLOOKUP(C28,'Datos - analisis de pago'!O40:P41,2,FALSE),0) -> 0 | E28: 0.5 | F28: 5 | G28: =SUM(F26:F28) -> 15
E29: =SUM(E4:E25) -> 17.5 | F29: =SUM(F4:F25) -> 88 | G29: =SUM(G5:G28) -> 103
D30: =IF(C2="Hipotecario",SUM(D4:D25),(SUM(D4:D19)+D24+D25+D26+D27+D28)) -> 0

Sheet Datos - analisis de pago
B3: Edad | E3: Municipio | L3: Cuotas
B4: 40 - 49 años | C4: 1 | E4: Guatemala | F4: 1 | H4: Coinciden direcciones | L4: Cuota nivelada
B5: 30 - 39 años | C5: 1 | E5: Santa Catarina Pinula | F5: 1.5 | H5: Si | I5: 1 | L5: Cuota de intereses
B6: 18 - 29 años | C6: 1.5 | E6: San José Pinula | F6: 1.5 | H6: No | I6: 4
B7: 70 años o mas | C7: 2 | E7: San José del Golfo | F7: 2
E8: Palencia | F8: 2
E9: Chinautla | F9: 2
E10: San Pedro Ayampuc | F10: 2
E11: Mixco | F11: 1
E12: San Pedro Sacatepéquez | F12: 1.5
E13: San Juan Sacatepéquez | F13: 1.5
E14: San Raymundo | F14: 1.5 | I14: Mejor | J14: Peor
E15: Chuarrancho | F15: 1.5 | I15: =(0.15*3)/0.15 -> 3 | J15: =(0.15*15)/0.15 -> 15
E16: Fraijanes | F16: 1
E17: Amatitlán | F17: 1.5
E18: Villa Nueva | F18: 1
E19: Villa Canales | F19: 1.5
E20: Petapa | F20: 1.5
B23: Estado civil | E23: Tiene dependientes | H23: capacidad de endeudamiento | L23: Esta orgulloso de sus actividades | O23: Dentro de sus egresos paga alguna deuda?
B24: Casado | C24: 1 | E24: Si | F24: 4 | H24: Q0 - Q1000 | I24: 10 | L24: Si | M24: 1 | O24: Si | P24: 4
B25: Soltero | C25: 4 | E25: No | F25: 1 | H25: Q1,001 - Q3,000 | I25: 4 | L25: No | M25: 4 | O25: No | P25: 1
B26: Viudo/a | C26: 3 | H26: Q3,001 - Q6,000 | I26: 3.5
H27: Q6,001 - Q10,000 | I27: 3
H28: Q10,001 - Q15,000 | I28: 2.5
H29: Q15,001 - Q25,000 | I29: 2.5
H30: Q25,001 en adelante | I30: 2
B32: Tiene cuenta en algun banco ? | E32: Tiene o ha tenido tarjeta de credito? | H32: La tiene al día? | K32: Es honrado? | N32: Cuantos créditos activos tiene? | R32: Posee cuotas atrasadas | V32: Cantidad de cuotas atrasadas
B33: Si | C33: 1 | E33: Si | F33: 0.5 | H33: Si | I33: 0.5 | K33: Si | L33: 0.5 | N33: 0 | O33: 0 | R33: Si | S33: 5 | V33: 0 | W33: 0
B34: No | C34: 3 | E34: No | F34: 3 | H34: No | I34: 7 | K34: No | L34: 7 | N34: 1 | O34: 0.5 | R34: No | S34: 0.5 | V34: 1 | W34: 0.5
N35: 2 | O35: 0.5 | V35: 2 | W35: 3
N36: 3 | O36: 1 | V36: 3 | W36: 4
N37: 4 | O37: 1.5 | V37: 4 | W37: 6
N38: 5+ | O38: 2 | V38: 5+ | W38: 7
B39: Tipo de propiedad | E39: Tiene alguna deuda sobre la propiedad | H39: Que logro tener algo propio! | L39: Origen | O39: Que logro tener algo propio!
B40: Terreno | C40: 0.5 | E40: Si | F40: 5 | H40: Si | I40: 0.5 | L40: Rodado | M40: 2 | O40: Si | P40: 0.5
B41: Lote | C41: 2 | E41: No | F41: 0.5 | H41: No | I41: 5 | L41: Agencia | M41: 0.5 | O41: No | P41: 5
B42: Casa | C42: 0.5
B43: Apartamento | C43: 0.5
B44: Bodega | C44: 3 | E44: Tiene IUSI al día? | H44: Cuantos trimestres adeuda? | K44: Impuesto de circulacion del año en curso pagado? | P44: Días en mora
B45: Edificio | C45: 5 | E45: Si | F45: 1 | H45: 1 | I45: 0.5 | K45: Si | L45: 0.5 | P45: 30 | Q45: 0.5
B46: Parqueo | C46: 2 | E46: No | F46: 5 | H46: 2 | I46: 2 | K46: No | L46: 5 | P46: 60 | Q46: 3
B47: Granja/ finca | C47: 5 | H47: 3 | I47: 4 | P47: 90+ | Q47: 5
H48: 4+ | I48: 5
A50: Cuota nivelada vs. Capacidad de endeudamiento | C50: Monto que adeuda | F50: Garantia propia
A51: 0.01 | B51: 1 | C51: 1 | F51: Si | G51: 1 | I51: Cuenta con alguna deuda sobre el vehiculo
A52: 0.02 | B52: 1 | C52: 1 | F52: No | G52: 2.5 | I52: Si | J52: 0.5
A53: 0.03 | B53: 1 | C53: 1 | I53: No | J53: 5
A54: 0.04 | B54: 1 | C54: 1
A55: 0.05 | B55: 1 | C55: 1
A56: 0.06 | B56: 1 | C56: 1
A57: 0.07 | B57: 1 | C57: 1
A58: 0.08 | B58: 1 | C58: 1
A59: 0.09 | B59: 1 | C59: 1
A60: 0.1 | B60: 1 | C60: 1
A61: 0.11 | B61: 1 | C61: 1
A62: 0.12 | B62: 1 | C62: 1
A63: 0.13 | B63: 1 | C63: 1
A64: 0.14 | B64: 1 | C64: 1
A65: 0.15 | B65: 1 | C65: 1
... A150: 1 | B150: 2.5 | C150: 0.5

Sheet Datos - analisis garantia
A1: 1
A2: 2
A3: 3
A4: 4
A5: 5
A6: 6
A7: 7
A8: 8
A9: 9
A10: 10
A11: 11
A12: 12
A13: 13
A14: 14 | C14: informacion general | D14: =SUM(L17:L18) -> 88
A15: 15
A16: 16 | C16: Edad | F16: Zona | I16: medio en el que nos vio
A17: 17 | C17: 40 - 49 años | D17: 5 | F17: Casco Urbano | G17: 3 | I17: Facebook | L17: =SUM(D17:D20) -> 65 | N17: Pregunta #1
A18: 18 | C18: 30 - 39 años | D18: 5 | F18: Ciudad Satelite | G18: 5 | I18: Instagram | L18: =SUM(G17:G20) -> 23 | N18: Si | O18: 5
A19: 19 | C19: 18 - 29 años | D19: 20 | F19: Interior Casco | G19: 7 | I19: Volantes | N19: No | O19: 15
A20: 20 | C20: 70 años o mas | D20: 35 | F20: Interior Rural | G20: 8 | I20: Activacion
A21: 21 | I21: Prensa
A22: 22
A23: 23
A24: 24 | C24: informacion laboral | D24: =D27+D28+D29+F27+F28+F31+F32+I27+I28+I29+I30+I31+I32+L27+L28+L29+L30+O27+O28+O29+R27+R28+R29+R30+R31+R32+U27+U28+U29+U30+U31+U32+X27+X28+AA28+AA29+AA30+AA31+AA32+AA33 -> 116
A25: 25
C26: Estado civil | E26: Tiene dependientes economicos? | H26: Cuantos dependientes? | K26: Ocupacion | N26: Inicio de labores | Q26: Ingresos | T26: Egresos | W26: Afiliacion al IGSS | Z26: capacidad de endeudamiento | AC26: cuota nivelada ideal | AE26: Pregunta #2
C27: Casado | D27: 1 | E27: Si | F27: 5 | H27: 0 | I27: 0 | K27: Empleado | L27: 3 | N27: 0-1 año | O27: 5 | Q27: Q1,000 - Q3,000 | R27: 5 | T27: Q1,000 - Q3,000 | U27: 1 | W27: Si | X27: 1 | Z27: Q0 - Q1000 | AA27: 8 | AE27: Si | AF27: 1
A28: 1960 | C28: Soltero | D28: 5 | E28: No | F28: 1 | H28: 1 | I28: 1 | K28: Dueño | L28: 1 | N28: 1-5 años | O28: 3 | Q28: Q3,001 - Q6,000 | R28: 4 | T28: Q3,001 - Q6,000 | U28: 2 | W28: No | X28: 5 | Z28: Q1,001 - Q3,000 | AA28: 5 | AE28: No | AF28: 5
A29: 1961 | C29: Viudo/a | D29: 3 | H29: 2 | I29: 2 | K29: Desempleado | L29: 5 | N29: 5-10 años | O29: 1 | Q29: Q6,001 - Q10,000 | R29: 3 | T29: Q6,001 - Q10,000 | U29: 3 | Z29: Q3,001 - Q6,000 | AA29: 4
A30: 1962 | E30: Tiene mascotas | H30: 3 | I30: 3 | K30: retirado | L30: 3 | Q30: Q10,001 - Q15,000 | R30: 2 | T30: Q10,001 - Q15,000 | U30: 4 | Z30: Q6,001 - Q10,000 | AA30: 3
A31: 1963 | E31: Si | F31: 5 | H31: 4 | I31: 4 | Q31: Q15,001 - Q25,000 | R31: 1 | T31: Q15,001 - Q25,000 | U31: 5 | Z31: Q10,001 - Q15,000 | AA31: 2
A32: 1964 | E32: No | F32: 1 | H32: 5+ | I32: 5 | Q32: Q25,001 en adelante | R32: 1 | T32: Q25,001 en adelante | U32: 6 | Z32: Q15,001 - Q25,000 | AA32: 1
A33: 1965 | Z33: Q25,001 en adelante | AA33: 1
A34: 1966
A35: 1967 | C35: Informacion crediticia
A36: 1968
A37: 1969 | C37: Tiene cuenta en algun banco ? | F37: Estados de cuenta | I37: Tiene o ha tenido tarjeta de credito? | L37: La tiene funcionando | O37: El dinero lo utilizara en ….? | S37: Ha tenido algun credito ? | V37: Vivienda propia ? | Y37: Vehiculo propio | AB37: Pregunta #3
A38: 1970 | C38: Si | D38: 2 | F38: Si | G38: 2 | I38: Si | J38: 2 | L38: Si | M38: 1 | O38: Capital de trabajo | P38: 3 | S38: hipotecario | V38: Si | W38: 2 | Y38: Si | Z38: 2 | AB38: Si | AC38: 1
A39: 1971 | C39: No | D39: 10 | F39: No | G39: 10 | I39: No | J39: 10 | L39: No | M39: 10 | O39: Salud o Medico | P39: 15 | S39: vehiculo | V39: No | W39: 10 | Y39: No | Z39: 10 | AB39: No | AC39: 5
A40: 1972 | O40: Consumo | P40: 20 | S40: consumo
A41: 1973 | O41: mejora de algo en inmubele o vehiculo | P41: 3 | S41: prestamista
A42: 1974 | O42: turismo | P42: 20
A43: 1975 | O43: Consolidacion de deudas | P43: 15
A44: 1976 | O44: Estudios | P44: 10
A45: 1977 | O45: Muerte de familiar | P45: 10
A46: 1978
A47: 1979 | C47: Informacion del credito
A48: 1980
A49: 1981 | C49: Tipo de credito | F49: garantia del credito | H49: La garantia es propia | K49: toma usted la decisión sobre el credito ? | N49: que espera usted de su credito? | P49: Pariente migrante ? | R49: si llegara a tener algun problema de pago tiene alguien que l@ apoye?
A50: 1982 | C50: leasing maquinaria | F50: Hipotecario | H50: Si | I50: 1 | K50: Si | L50: 1 | N50: rapido y seguro | P50: Si | R50: Si
A51: 1983 | C51: Factoraje internacional | F51: Vehículo | H51: No | I51: 5 | K51: No | L51: 5 | N51: barato | P51: No | R51: No
A52: 1984 | C52: Sin fiador | N52: negociable
A53: 1985 | C53: Fiduciario | N53: sano
A54: 1986 | C54: Hipotecario | N54: cuota nivelada
A55: 1987 | C55: Prendario
A56: 1988
A57: 1989
A58: 1990 | C58: Informacion de la garantia hipotecaria
A59: 1991
A60: 1992 | C60: tipo de propiedad | F60: cuenta con alguna deuda sobre la propiedad ? | J60: tiene construccion ? | M60: Zona | P60: Pregunta #4
A61: 1993 | C61: Terreno | D61: 5 | F61: Si | G61: 30 | J61: Si | K61: 1 | M61: Casco Urbano | N61: 3 | P61: Si | Q61: 5
A62: 1994 | C62: Lote | D62: 15 | F62: No | G62: 6 | J62: No | K62: 5 | M62: Ciudad Satelite | N62: 5 | P62: No | Q62: 9
A63: 1995 | C63: Casa | D63: 5 | M63: Interior Casco | N63: 7
A64: 1996 | C64: Apartamento | D64: 5 | M64: Interior Rural | N64: 8
A65: 1997 | C65: Bodega | D65: 20
A66: 1998 | C66: Edificio | D66: 40
A67: 1999 | C67: Parqueo | D67: 15
A68: 2000 | C68: Granja/ finca | D68: 40
A69: 2001
A70: 2002
A71: 2003 | C71: Marca del vehiculo | F71: Origen | I71: su vehiculo se encuentra en estado | L71: le ha realizado alguna modificacion estetica? | P71: le ha colocado accesorios o equipo de sonido mejorado | U71: cuenta con alguna deuda sobre el vehículo ? | Y71: Pregunta #5
A72: 2004 | F72: Agencia | G72: 3 | I72: bueno | J72: 3 | L72: Si | M72: 5 | P72: Si | Q72: 1 | U72: Si | V72: 20 | Y72: Si | Z72: 4
A73: 2005 | F73: Rodado | G73: 20 | I73: medio | J73: 7 | L73: No | M73: 1 | P73: No | Q73: 3 | U73: No | V73: 3 | Y73: No | Z73: 19
A74: 2006 | I74: malo | J74: 10
A75: 2007 | I75: daño estetico | J75: 15
A76: 2008 | I76: daño mecanico | J76: 20
A77: 2009
A78: 2010
A79: 2011
A80: 2012
A81: 2013
A82: 2014
A83: 2015
A84: 2016
A85: 2017
A86: 2018
A87: 2019
A89: Alta Verapaz
A90: Baja Verapaz
A91: Chimaltenango
A92: Chiquimula
A93: El Progreso
A94: Escuintla
A95: Guatemala
A96: Huehuetenango
A97: Izabal
A98: Jalapa
A99: Jutiapa
A100: Petén
... A110: Zacapa
...

Sheet Analisis garantia
J2: CATALOGO DE RIESGO
B7: Nombre:
B8: DPI: | V8: NIT:
AT9: Ideal | AY9: Peor
B10: Edad del solicitante | V10: =FORMULARIO!K9 -> 0 | AO10: =IFERROR(VLOOKUP(V10,'Datos - analisis garantia'!C17:D20,2,FALSE),0) -> 0 | AT10: 5 | AY10: 35
B11: Residencia | V11: =FORMULARIO!J15 -> 0 | AO11: =IFERROR(VLOOKUP(V11,'Datos - analisis garantia'!D179:F195,2,FALSE),0) -> 0 | AT11: 5 | AY11: 35 | CB11: Informacion general | CN11: =SUM(AO10:AS11) -> 0 | CQ11: 0.25 | CT11: =CN11*CQ11 -> 0
B12: Pregunta #1 | V12: =FORMULARIO!K21 -> 0 | AO12: =IFERROR(VLOOKUP(V12,'Datos - analisis garantia'!N18:O19,2,FALSE),0) -> 0 | AT12: 5 | AY12: 15
B13: Estado civil | V13: =FORMULARIO!C13 -> 0 | AO13: =IFERROR(VLOOKUP(V13,'Datos - analisis garantia'!C27:D29,2,FALSE),0) -> 0 | AT13: 1 | AY13: 5 | CB13: Informacion laboral | CN13: =SUM(AO13:AS23) -> 0 | CQ13: 0.15 | CT13: =CN13*CQ13 -> 0
B14: Tiene dependientes | V14: =FORMULARIO!F36 -> 0 | AO14: =IFERROR(VLOOKUP(V14,'Datos - analisis garantia'!E27:F28,2,FALSE),0) -> 0 | AT14: 1 | AY14: 5 | BF14: =IF(BR22="Hipotecario",IF(CA22=0,"",IF(CA22<=100,"A",IF(CA22<=160,"B",IF(CA22<=240,"C",IF(CA22<=340,"D",""))))),IF(CA22=0,"",IF(CA22<=100,"A",IF(CA22<=160,"B",IF(CA22<=240,"C",IF(CA22<=340,"D","")))))) -> A | CB14: Informacion crediticia | CN14: =SUM(AO24:AS30) -> 15 | CQ14: 0.25 | CT14: =CN14*CQ14 -> 3.75
B15: Pregunta #2 | V15: =FORMULARIO!D38 -> 0 | AO15: =IFERROR(VLOOKUP(V15,'Datos - analisis garantia'!AE27:AF28,2,FALSE),0) -> 0 | AT15: 1 | AY15: 5 | CB15: Hipotecario | CN15: =SUM(AO32:AS34) -> 0 | CQ15: 0.35 | CT15: =CN15*CQ15 -> 0 | CX15: =CT15+CT14+CT13+CT11 -> 3.75
B16: Cuantos dependientes | V16: =FORMULARIO!J36 -> 0 | AO16: =VLOOKUP(V16,'Datos - analisis garantia'!H27:I32,2,FALSE) -> 0 | AT16: 0 | AY16: 5 | BF16: =IF(BF15="","","Tasa a Ofrecer") | CB16: Vehiculo | CN16: =SUM(AO36:AS40) -> 0 | CQ16: 0.35 | CT16: =CN16*CQ16 -> 0 | CX16: =CT16+CT14+CT13+CT11 -> 3.75
B17: Ocupacion | V17: =FORMULARIO!C26 -> 0 | AO17: =IFERROR(VLOOKUP(V17,'Datos - analisis garantia'!K27:L30,2,FALSE),0) -> 0 | AT17: 1 | AY17: 5 | BF17: =IF(BF14="","","Tasa a Ofrecer") -> Tasa a Ofrecer | CN17: =SUM(CN11:CP15) -> 15
B18: Inicio de labores | V18: =FORMULARIO!C28 -> 0 | AO18: =IFERROR(VLOOKUP(V18,'Datos - analisis garantia'!N27:O29,2,FALSE),0) -> 0 | AT18: 1 | AY18: 5 | BF18: =IF(BR22="Hipotecario",IF(BF14="A","1% - 1.5%",IF(BF14="B","1.6% - 2%",IF(BF14="C","2.1% - 2.5%",IF(BF14="D","3%","")))),IF(BF14="A","2.5% - 3.5%",IF(BF14="B","3.6% - 5.9%",IF(BF14="C","6% - 6.9%",IF(BF14="D","7%",""))))) -> 2.5% - 3.5% | CN18: =CN11/CN17 -> 0
B19: Ingresos | V19: =FORMULARIO!D30 -> 0 | AO19: =IFERROR(VLOOKUP(V19,'Datos - analisis garantia'!Q27:R32,2,FALSE),0) -> 0 | AT19: 1 | AY19: 5 | CN19: =CN13/CN17 -> 0
B20: Egresos | V20: =FORMULARIO!I30 -> 0 | AO20: =IFERROR(VLOOKUP(V20,'Datos - analisis garantia'!T27:U32,2,FALSE),0) -> 0 | AT20: 1 | AY20: 6 | CN20: =CN14/CN17 -> 1
B21: Afiliacion al IGSS | V21: =FORMULARIO!H28 -> 0 | AO21: =IFERROR(VLOOKUP(V21,'Datos - analisis garantia'!W27:X28,2,FALSE),0) -> 0 | AT21: 1 | AY21: 5 | CN21: =CN15/CN17 -> 0
B22: Capacidad de endeudamiento | V22: =FORMULARIO!G32 -> 0 | AO22: =IFERROR(VLOOKUP(V22,'Datos - analisis garantia'!Z27:AA33,2,FALSE),0) -> 0 | AT22: 1 | AY22: 5 | BG22: Tipo de credito | BR22: =FORMULARIO!D61 -> Vehículo | CA22: =IF(BR22="Hipotecario",BO23+BO24,BO23+BO25) -> 15
BG23: Info general | BO23: =AO10+AO11+AO13+AO14+AO15+AO16+AO17+AO18+AO19+AO20+AO21+AO22+AO24+AO25+AO26+AO27+AO28+AO29+AO30+AO12+AO31 -> 15
B24: Tiene cuenta en algun banco ? | V24: =FORMULARIO!E43 -> 0 | AO24: =IFERROR(VLOOKUP(V24,'Datos - analisis garantia'!C38:D39,2,FALSE),0) -> 0 | AT24: 2 | AY24: 10 | BG24: Hipotecario | BO24: =AO32+AO33+AO34+AO35 -> 0
B25: Estados de cuenta | V25: =FORMULARIO!I43 -> 0 | AO25: =IFERROR(VLOOKUP(V25,'Datos - analisis garantia'!F38:G39,2,FALSE),0) -> 0 | AT25: 2 | AY25: 10 | BG25: Vehiculo | BO25: =AO38+AO39+AO40+AO37+AO36+AO41 -> 0
B26: Tiene o ha tenido tarjeta de credito? | V26: =FORMULARIO!F45 -> 0 | AO26: =IFERROR(VLOOKUP(V26,'Datos - analisis garantia'!I38:J39,2,FALSE),0) -> 0 | AT26: 2 | AY26: 10
B27: La tiene funcionando | V27: =FORMULARIO!I45 -> 0 | AO27: =IFERROR(VLOOKUP(V27,'Datos - analisis garantia'!L38:M39,2,FALSE),0) -> 0 | AT27: 1 | AY27: 10
B28: El dinero lo utilizara en ….? | V28: =FORMULARIO!E47 -> Salud o Medico | AO28: =IFERROR(VLOOKUP(V28,'Datos - analisis garantia'!O38:P45,2,FALSE),0) -> 15 | AT28: 3 | AY28: 20 | BH28: Hipotecario | BR28: Vehiculo | CI28: =(0.35*51)/0.15 -> 119
B29: Vivienda propia | V29: =FORMULARIO!H55 -> 0 | AO29: =IFERROR(VLOOKUP(V29,'Datos - analisis garantia'!V38:W39,2,FALSE),0) -> 0 | AT29: 2 | AY29: 10 | BH29: A | BI29: 25 | BR29: 25 | CI29: =SUM(AT32:AW35) -> 21
B30: vehiculo propio? | V30: =FORMULARIO!K55 -> 0 | AO30: =IFERROR(VLOOKUP(V30,'Datos - analisis garantia'!Y38:Z39,2,FALSE),0) -> 0 | AT30: 2 | AY30: 10 | BH30: B
B31: Pregunta #3 | V31: =FORMULARIO!C57 -> 0 | AO31: =IFERROR(VLOOKUP(V31,'Datos - analisis garantia'!AB38:AC39,2,FALSE),0) -> 0 | AT31: 1 | AY31: 5 | BH31: C
B32: Tipo de propiedad | V32: =FORMULARIO!D86 -> 0 | AO32: =IFERROR(VLOOKUP(V32,'Datos - analisis garantia'!C61:D68,2,FALSE),0) -> 0 | AT32: 5 | AY32: 40 | BH32: D | BI32: 118 | BR32: 117
B33: Municipio | V33: =FORMULARIO!H88 -> 0 | AO33: =IFERROR(VLOOKUP(V33,'Datos - analisis garantia'!A179:B195,2,FALSE),0) -> 0 | AT33: 5 | AY33: 40
B34: Cuenta con alguna deuda sobre la propiedad ? | V34: =FORMULARIO!L92 -> 0 | AO34: =IFERROR(VLOOKUP(V34,'Datos - analisis garantia'!F61:G62,2,FALSE),0) -> 0 | AT34: 6 | AY34: 30
B35: Pregunta #4 | V35: =FORMULARIO!C57 -> 0 | AO35: =IFERROR(VLOOKUP(V35,'Datos - analisis garantia'!P61:Q62,2,FALSE),0) -> 0 | AT35: 5 | AY35: 9
B36: Marca del vehiculo | V36: =FORMULARIO!B105 -> 0 | AO36: =IFERROR(VLOOKUP(V36,'Datos - analisis garantia'!A112:B142,2,FALSE),0) -> 0 | AT36: 5 | AY36: 20
B37: Modelo | V37: =FORMULARIO!G105 -> 0 | AO37: =IFERROR(VLOOKUP(V37,'Datos - analisis garantia'!A154:B175,2,FALSE),0) -> 0 | AT37: 3 | AY37: 20
B38: Origen del vehículo | V38: =FORMULARIO!D107 -> 0 | AO38: =IFERROR(VLOOKUP(V38,'Datos - analisis garantia'!F72:G73,2,FALSE),0) -> 0 | AT38: 3 | AY38: 20 | BH38: A | BI38: 45 | BR38: 43
B39: Su vehículo se encuentra en estado | V39: =FORMULARIO!K107 -> 0 | AO39: =IFERROR(VLOOKUP(V39,'Datos - analisis garantia'!I72:J76,2,FALSE),0) -> 0 | AT39: 3 | AY39: 20 | BH39: B | BI39: 65 | BR39: 63
B40: cuenta con alguna deuda sobre el vehículo ? | V40: =FORMULARIO!G113 -> 0 | AO40: =IFERROR(VLOOKUP(V40,'Datos - analisis garantia'!U72:V73,2,FALSE),0) -> 0 | AT40: 3 | AY40: 20 | BH40: C | BI40: 85 | BR40: 83
B41: Pregunta #5 | V41: =FORMULARIO!E121 -> 0 | AO41: =IFERROR(VLOOKUP(V41,'Datos - analisis garantia'!Y72:Z73,2,FALSE),0) -> 0 | AT41: 4 | AY41: 19 | BH41: D | BI41: 105 | BR41: 103
BH46: A | BI46: 50 | BU46: Informacion general | CH46: =SUM(AT10:AX12) -> 15 | CK46: =SUM(AY10:BC12) -> 85
BH47: B | BI47: 75 | BU47: Informacion laboral | CH47: =SUM(AT13:AX23) -> 9 | CK47: =SUM(AY13:BC23) -> 51
BH48: C | BI48: 100 | BU48: Informacion crediticia | CH48: =SUM(AT24:AX30) -> 14 | CK48: =SUM(AY24:BC30) -> 80
BH49: D | BI49: 125 | BU49: Hipotecario | CH49: =SUM(AT32:AX34) -> 16 | CK49: =SUM(AY32:BC34) -> 110
B50: Referencia para colocar rango de capacidad de endeudamiento | BU50: Vehiculo | CH50: =SUM(AT36:AX40) -> 17 | CK50: =SUM(AY36:BC40) -> 100
B51: Ingresos | P51: Egresos | CH51: =SUM(CH46:CJ49) -> 54 | CK51: =SUM(CK46:CM49) -> 326
CH52: =CK51/3 -> 108.66667
I53: =IFERROR((G51-U51)/(G51),"") | M53: =IF(I53="","","Capacidad de endeudamiento")
